Workbook
Name TasaVentasEEUU: Supuestos!$C$5
Name FleteLb: Supuestos!$C$6
Name IVA: Supuestos!$C$7
Name RecargoCIF: Supuestos!$C$8
Name LimiteFranquicia: Supuestos!$C$9
Name EnviosCasillero: Supuestos!$C$10
Name GestionEnvio: Supuestos!$C$11
Name DescCasaRivas: Supuestos!$C$12
Name Contingencia: Supuestos!$C$13
Name Integrantes: Supuestos!$C$14
Name Presupuesto: Supuestos!$C$15
Name MermaImpresion: Supuestos!$C$16
Name RendimientoGH: Supuestos!$C$17
Name GramosRollo: Supuestos!$C$18
Name Miembros: Supuestos!$B$23:$B$26

Sheet Resumen
A1: Presupuesto · SCARA MathBot
A2: SCARA de HowToMechatronics con columna Z recortada y cabezal de disco (versión final): plumón, electroimán y sensor inductivo. Precios locales de Electrónica 2001 y Steren verificados en línea el 06-oct-2026; el resto, cotizar o estimado. Amazon con impuestos y casillero.
A4: Indicadores
A5: Presupuesto del equipo | C5: =Presupuesto | D5: ← editar en Supuestos
A6: Gastado a la fecha | C6: ='Registro de gastos'!$L$10
A7: Pendiente por comprar | C7: =SUM('Lista de materiales'!$W$5:$W$54)
A8: Contingencia sobre lo pendiente | C8: =C7*Contingencia
A9: Proyección final (con contingencia) | C9: =C6+C7+C8
A10: Presupuesto restante | C10: =C5-C9 | D10: =IF(C10<0,"Se pasan del presupuesto","Dentro del presupuesto")
A11: Uso del presupuesto | C11: =IF(C5>0,C9/C5,0)
A12: Costo por integrante | C12: =IF(Integrantes>0,C9/Integrantes,0)
A13: Ahorro por lo que ya tenemos | C13: =SUMIFS('Lista de materiales'!$T$5:$T$54,'Lista de materiales'!$U$5:$U$54,"Ya lo tenemos")
A14: Pendiente si todo se compra donde sale más barato | C14: =SUMIFS('Lista de materiales'!$AC$5:$AC$54,'Lista de materiales'!$U$5:$U$54,"Por comprar")+SUMIFS('Lista de materiales'!$AC$5:$AC$54,'Lista de materiales'!$U$5:$U$54,"Cotizado") | D14: ← supone que las tiendas 'Cotizar' tienen el producto al precio estimado
A15: Ahorro potencial (eligiendo siempre lo más barato) | C15: =MAX(C7-C14,0)
A18: Por categoría
A19: Categoría | B19: Estimado | C19: Ya lo tenemos | D19: Gastado | E19: Pendiente | F19: Proyección | G19: % del total
A20: Estructura y eje Z | B20: =SUMIFS('Lista de materiales'!$T$5:$T$54,'Lista de materiales'!$B$5:$B$54,A20,'Lista de materiales'!$U$5:$U$54,"<>No comprar") | C20: =SUMIFS('Lista de materiales'!$T$5:$T$54,'Lista de materiales'!$B$5:$B$54,A20,'Lista de materiales'!$U$5:$U$54,"Ya lo tenemos") | D20: =SUMIFS('Lista de materiales'!$V$5:$V$54,'Lista de materiales'!$B$5:$B$54,A20) | E20: =SUMIFS('Lista de materiales'!$W$5:$W$54,'Lista de materiales'!$B$5:$B$54,A20) | F20: =SUMIFS('Lista de materiales'!$X$5:$X$54,'Lista de materiales'!$B$5:$B$54,A20) | G20: =IF($F$28>0,F20/$F$28,0)
A21: Rodamientos | B21: =SUMIFS('Lista de materiales'!$T$5:$T$54,'Lista de materiales'!$B$5:$B$54,A21,'Lista de materiales'!$U$5:$U$54,"<>No comprar") | C21: =SUMIFS('Lista de materiales'!$T$5:$T$54,'Lista de materiales'!$B$5:$B$54,A21,'Lista de materiales'!$U$5:$U$54,"Ya lo tenemos") | D21: =SUMIFS('Lista de materiales'!$V$5:$V$54,'Lista de materiales'!$B$5:$B$54,A21) | E21: =SUMIFS('Lista de materiales'!$W$5:$W$54,'Lista de materiales'!$B$5:$B$54,A21) | F21: =SUMIFS('Lista de materiales'!$X$5:$X$54,'Lista de materiales'!$B$5:$B$54,A21) | G21: =IF($F$28>0,F21/$F$28,0)
A22: Transmisión | B22: =SUMIFS('Lista de materiales'!$T$5:$T$54,'Lista de materiales'!$B$5:$B$54,A22,'Lista de materiales'!$U$5:$U$54,"<>No comprar") | C22: =SUMIFS('Lista de materiales'!$T$5:$T$54,'Lista de materiales'!$B$5:$B$54,A22,'Lista de materiales'!$U$5:$U$54,"Ya lo tenemos") | D22: =SUMIFS('Lista de materiales'!$V$5:$V$54,'Lista de materiales'!$B$5:$B$54,A22) | E22: =SUMIFS('Lista de materiales'!$W$5:$W$54,'Lista de materiales'!$B$5:$B$54,A22) | F22: =SUMIFS('Lista de materiales'!$X$5:$X$54,'Lista de materiales'!$B$5:$B$54,A22) | G22: =IF($F$28>0,F22/$F$28,0)
A23: Motores y electrónica | B23: =SUMIFS('Lista de materiales'!$T$5:$T$54,'Lista de materiales'!$B$5:$B$54,A23,'Lista de materiales'!$U$5:$U$54,"<>No comprar") | C23: =SUMIFS('Lista de materiales'!$T$5:$T$54,'Lista de materiales'!$B$5:$B$54,A23,'Lista de materiales'!$U$5:$U$54,"Ya lo tenemos") | D23: =SUMIFS('Lista de materiales'!$V$5:$V$54,'Lista de materiales'!$B$5:$B$54,A23) | E23: =SUMIFS('Lista de materiales'!$W$5:$W$54,'Lista de materiales'!$B$5:$B$54,A23) | F23: =SUMIFS('Lista de materiales'!$X$5:$X$54,'Lista de materiales'!$B$5:$B$54,A23) | G23: =IF($F$28>0,F23/$F$28,0)
A24: Cabezal de disco | B24: =SUMIFS('Lista de materiales'!$T$5:$T$54,'Lista de materiales'!$B$5:$B$54,A24,'Lista de materiales'!$U$5:$U$54,"<>No comprar") | C24: =SUMIFS('Lista de materiales'!$T$5:$T$54,'Lista de materiales'!$B$5:$B$54,A24,'Lista de materiales'!$U$5:$U$54,"Ya lo tenemos") | D24: =SUMIFS('Lista de materiales'!$V$5:$V$54,'Lista de materiales'!$B$5:$B$54,A24) | E24: =SUMIFS('Lista de materiales'!$W$5:$W$54,'Lista de materiales'!$B$5:$B$54,A24) | F24: =SUMIFS('Lista de materiales'!$X$5:$X$54,'Lista de materiales'!$B$5:$B$54,A24) | G24: =IF($F$28>0,F24/$F$28,0)
A25: Electrónica MathBot | B25: =SUMIFS('Lista de materiales'!$T$5:$T$54,'Lista de materiales'!$B$5:$B$54,A25,'Lista de materiales'!$U$5:$U$54,"<>No comprar") | C25: =SUMIFS('Lista de materiales'!$T$5:$T$54,'Lista de materiales'!$B$5:$B$54,A25,'Lista de materiales'!$U$5:$U$54,"Ya lo tenemos") | D25: =SUMIFS('Lista de materiales'!$V$5:$V$54,'Lista de materiales'!$B$5:$B$54,A25) | E25: =SUMIFS('Lista de materiales'!$W$5:$W$54,'Lista de materiales'!$B$5:$B$54,A25) | F25: =SUMIFS('Lista de materiales'!$X$5:$X$54,'Lista de materiales'!$B$5:$B$54,A25) | G25: =IF($F$28>0,F25/$F$28,0)
A26: Tornillería | B26: =SUMIFS('Lista de materiales'!$T$5:$T$54,'Lista de materiales'!$B$5:$B$54,A26,'Lista de materiales'!$U$5:$U$54,"<>No comprar") | C26: =SUMIFS('Lista de materiales'!$T$5:$T$54,'Lista de materiales'!$B$5:$B$54,A26,'Lista de materiales'!$U$5:$U$54,"Ya lo tenemos") | D26: =SUMIFS('Lista de materiales'!$V$5:$V$54,'Lista de materiales'!$B$5:$B$54,A26) | E26: =SUMIFS('Lista de materiales'!$W$5:$W$54,'Lista de materiales'!$B$5:$B$54,A26) | F26: =SUMIFS('Lista de materiales'!$X$5:$X$54,'Lista de materiales'!$B$5:$B$54,A26) | G26: =IF($F$28>0,F26/$F$28,0)
A27: Impresión y varios | B27: =SUMIFS('Lista de materiales'!$T$5:$T$54,'Lista de materiales'!$B$5:$B$54,A27,'Lista de materiales'!$U$5:$U$54,"<>No comprar") | C27: =SUMIFS('Lista de materiales'!$T$5:$T$54,'Lista de materiales'!$B$5:$B$54,A27,'Lista de materiales'!$U$5:$U$54,"Ya lo tenemos") | D27: =SUMIFS('Lista de materiales'!$V$5:$V$54,'Lista de materiales'!$B$5:$B$54,A27) | E27: =SUMIFS('Lista de materiales'!$W$5:$W$54,'Lista de materiales'!$B$5:$B$54,A27) | F27: =SUMIFS('Lista de materiales'!$X$5:$X$54,'Lista de materiales'!$B$5:$B$54,A27) | G27: =IF($F$28>0,F27/$F$28,0)
A28: Total | B28: =SUM(B20:B27) | C28: =SUM(C20:C27) | D28: =SUM(D20:D27) | E28: =SUM(E20:E27) | F28: =SUM(F20:F27) | G28: =SUM(G20:G27)
A30: Por fuente (lo que falta comprar) | E30: Por prioridad
A31: Fuente | B31: Pendiente | C31: Proyección | E31: Prioridad | F31: Pendiente | G31: Proyección
A32: Local | B32: =SUMIFS('Lista de materiales'!$W$5:$W$54,'Lista de materiales'!$S$5:$S$54,A32) | C32: =SUMIFS('Lista de materiales'!$X$5:$X$54,'Lista de materiales'!$S$5:$S$54,A32) | E32: Obligatorio | F32: =SUMIFS('Lista de materiales'!$W$5:$W$54,'Lista de materiales'!$H$5:$H$54,E32) | G32: =SUMIFS('Lista de materiales'!$X$5:$X$54,'Lista de materiales'!$H$5:$H$54,E32)
A33: Amazon | B33: =SUMIFS('Lista de materiales'!$W$5:$W$54,'Lista de materiales'!$S$5:$S$54,A33) | C33: =SUMIFS('Lista de materiales'!$X$5:$X$54,'Lista de materiales'!$S$5:$S$54,A33) | E33: Recomendado | F33: =SUMIFS('Lista de materiales'!$W$5:$W$54,'Lista de materiales'!$H$5:$H$54,E33) | G33: =SUMIFS('Lista de materiales'!$X$5:$X$54,'Lista de materiales'!$H$5:$H$54,E33)
E34: Opcional | F34: =SUMIFS('Lista de materiales'!$W$5:$W$54,'Lista de materiales'!$H$5:$H$54,E34) | G34: =SUMIFS('Lista de materiales'!$X$5:$X$54,'Lista de materiales'!$H$5:$H$54,E34)
A35: Valor en factura Amazon por comprar (USD) | C35: =SUM('Lista de materiales'!$AB$5:$AB$54)
A36: Valor por envío (según número de envíos) | C36: =IF(EnviosCasillero>0,C35/EnviosCasillero,C35) | E36: Los opcionales empiezan en 'No comprar': no suman hasta que cambien su estado.
A37: =IF(C36>LimiteFranquicia,"Cada envío supera USD 300: dividan la compra en más envíos para pagar solo IVA.","Cada envío queda bajo USD 300: solo pagan 13 % de IVA en aduana.")
A39: Pagado por integrante
A40: Integrante | B40: Pagado | C40: Le toca (proyección / integrantes) | D40: Diferencia
A41: =INDEX(Miembros,1) | B41: =SUMIFS('Registro de gastos'!$F$10:$F$400,'Registro de gastos'!$G$10:$G$400,A41) | C41: =$C$12 | D41: =B41-C41
A42: =INDEX(Miembros,2) | B42: =SUMIFS('Registro de gastos'!$F$10:$F$400,'Registro de gastos'!$G$10:$G$400,A42) | C42: =$C$12 | D42: =B42-C42
A43: =INDEX(Miembros,3) | B43: =SUMIFS('Registro de gastos'!$F$10:$F$400,'Registro de gastos'!$G$10:$G$400,A43) | C43: =$C$12 | D43: =B43-C43
A44: =INDEX(Miembros,4) | B44: =SUMIFS('Registro de gastos'!$F$10:$F$400,'Registro de gastos'!$G$10:$G$400,A44) | C44: =$C$12 | D44: =B44-C44
A46: Diferencia positiva = ha puesto más de lo que le toca.
A49: Cómo usarlo
A50: 1. En Supuestos: presupuesto, nombres del equipo, número de envíos del casillero.
A51: 2. En Lista de materiales marquen el Estado de cada fila: 'Ya lo tenemos' (no se compra), 'Cotizado' (actualicen el precio local), 'Comprado'.
A52: 3. Cambien 'Fuente elegida' a Local o Amazon; si se pinta naranja, la otra opción sale más barata.
A53: 4. Cada pago va a Registro de gastos con el ID del ítem: el resumen y 'Gastado real' se actualizan solos.
A54: 5. En Impresión 3D marquen las piezas impresas; los rollos de filamento a comprar salen de ahí.

Sheet Lista de materiales
A1: Lista de materiales · SCARA MathBot (HowToMechatronics + cabezal de disco)
A2: Editables (amarillo, texto azul): cantidad, precios, fuente elegida, estado y responsable. Negro = fórmula. Verde = viene de otra hoja. 'Total Amazon puesto en SV' incluye impuesto de EE. UU., flete del casillero e IVA de aduana (ver Supuestos). Precios consultados el 06-oct-2026.
A4: ID | B4: Categoría | C4: Componente | D4: Especificación / modelo | E4: Uso en el robot | F4: Origen | G4: Cant. | H4: Prioridad | I4: Tienda local sugerida | J4: Precio local (USD/paq.) | K4: Unid./paq. local | L4: Precio local: verificación | M4: Precio Amazon (USD/paq.) | N4: Unid./paq. Amazon | O4: Peso paq. (lb) | P4: Total local (USD) | Q4: Total Amazon puesto en SV (USD) | R4: Opción más barata | S4: Fuente elegida | T4: Costo estimado (USD) | U4: Estado | V4: Gastado real (USD) | W4: Pendiente (USD) | X4: Proyección (USD) | Y4: Responsable | Z4: Enlace Amazon | AA4: Notas / fuente del precio | AB4: Valor factura Amazon (USD) | AC4: Opción más barata (USD)
A5: MEC-01 | B5: Estructura y eje Z | C5: Varilla lisa Ø10 mm | D5: Acero endurecido, 300 mm (cortar) | E5: 4 guías de la columna Z | F5: HTM | G5: 4 | H5: Obligatorio | I5: Creativo 3D (repuestos de impresoras) | J5: 8 | K5: 1 | L5: Cotizar (estimado) | M5: 17.99 | N5: 4 | O5: 1.8 | P5: =IF(J5="","",ROUNDUP(G5/K5,0)*J5*(1-IF(ISNUMBER(SEARCH("Casa Rivas",I5)),DescCasaRivas,0))) | Q5: =IF(M5="","",ROUNDUP(G5/N5,0)*(M5*(1+TasaVentasEEUU)+O5*FleteLb*(1+IVA)+M5*(1+RecargoCIF)*IVA)) | R5: =IF(AND(ISNUMBER(P5),ISNUMBER(Q5)),IF(P5<=Q5,"Local","Amazon"),IF(ISNUMBER(P5),"Local",IF(ISNUMBER(Q5),"Amazon","—"))) | S5: Amazon | T5: =IF(S5="Amazon",IF(ISNUMBER(Q5),Q5,0),IF(ISNUMBER(P5),P5,0)) | U5: Por comprar | V5: =SUMIFS('Registro de gastos'!$F$10:$F$400,'Registro de gastos'!$B$10:$B$400,A5) | W5: =IF(OR(U5="Por comprar",U5="Cotizado"),MAX(T5-V5,0),0) | X5: =V5+W5 | Z5: https://www.amazon.com/dp/B0D2312R72 | AA5: HTM usa 400 mm. Con el cabezal de disco v3 bastan 250 mm (NEMA estándar en J2) o 240 mm (NEMA corto): comprar 300 y cortar. | AB5: =IF(AND(S5="Amazon",ISNUMBER(M5),W5>0),ROUNDUP(G5/N5,0)*M5,0) | AC5: =IF(AND(ISNUMBER(P5),ISNUMBER(Q5)),MIN(P5,Q5),IF(ISNUMBER(P5),P5,IF(ISNUMBER(Q5),Q5,0)))
A6: MEC-02 | B6: Estructura y eje Z | C6: Rodamiento lineal LM10UU | D6: 10 × 19 × 29 mm | E6: Plataforma Z (desliza en las varillas) | F6: HTM | G6: 4 | H6: Obligatorio | I6: Creativo 3D / CEROSA | J6: 3 | K6: 1 | L6: Cotizar (estimado) | M6: 7.49 | N6: 4 | O6: 0.25 | P6: =IF(J6="","",ROUNDUP(G6/K6,0)*J6*(1-IF(ISNUMBER(SEARCH("Casa Rivas",I6)),DescCasaRivas,0))) | Q6: =IF(M6="","",ROUNDUP(G6/N6,0)*(M6*(1+TasaVentasEEUU)+O6*FleteLb*(1+IVA)+M6*(1+RecargoCIF)*IVA)) | R6: =IF(AND(ISNUMBER(P6),ISNUMBER(Q6)),IF(P6<=Q6,"Local","Amazon"),IF(ISNUMBER(P6),"Local",IF(ISNUMBER(Q6),"Amazon","—"))) | S6: Amazon | T6: =IF(S6="Amazon",IF(ISNUMBER(Q6),Q6,0),IF(ISNUMBER(P6),P6,0)) | U6: Por comprar | V6: =SUMIFS('Registro de gastos'!$F$10:$F$400,'Registro de gastos'!$B$10:$B$400,A6) | W6: =IF(OR(U6="Por comprar",U6="Cotizado"),MAX(T6-V6,0),0) | X6: =V6+W6 | Z6: https://www.amazon.com/dp/B0D5BHVY9W | AB6: =IF(AND(S6="Amazon",ISNUMBER(M6),W6>0),ROUNDUP(G6/N6,0)*M6,0) | AC6: =IF(AND(ISNUMBER(P6),ISNUMBER(Q6)),MIN(P6,Q6),IF(ISNUMBER(P6),P6,IF(ISNUMBER(Q6),Q6,0)))
A7: MEC-03 | B7: Estructura y eje Z | C7: Husillo T8 con tuerca de latón | D7: Tr8×8, 300 mm (avance 8 mm/rev) | E7: Eje Z | F7: HTM | G7: 1 | H7: Obligatorio | I7: Creativo 3D | J7: 15 | K7: 1 | L7: Cotizar (estimado) | M7: 11.99 | N7: 2 | O7: 0.6 | P7: =IF(J7="","",ROUNDUP(G7/K7,0)*J7*(1-IF(ISNUMBER(SEARCH("Casa Rivas",I7)),DescCasaRivas,0))) | Q7: =IF(M7="","",ROUNDUP(G7/N7,0)*(M7*(1+TasaVentasEEUU)+O7*FleteLb*(1+IVA)+M7*(1+RecargoCIF)*IVA)) | R7: =IF(AND(ISNUMBER(P7),ISNUMBER(Q7)),IF(P7<=Q7,"Local","Amazon"),IF(ISNUMBER(P7),"Local",IF(ISNUMBER(Q7),"Amazon","—"))) | S7: Amazon | T7: =IF(S7="Amazon",IF(ISNUMBER(Q7),Q7,0),IF(ISNUMBER(P7),P7,0)) | U7: Por comprar | V7: =SUMIFS('Registro de gastos'!$F$10:$F$400,'Registro de gastos'!$B$10:$B$400,A7) | W7: =IF(OR(U7="Por comprar",U7="Cotizado"),MAX(T7-V7,0),0) | X7: =V7+W7 | Z7: https://www.amazon.com/dp/B08JPPC1TZ | AA7: HTM lo corta a 380 mm para varillas de 400; con varillas de 250 mm cortar a ≈230 mm. El paquete trae 2. | AB7: =IF(AND(S7="Amazon",ISNUMBER(M7),W7>0),ROUNDUP(G7/N7,0)*M7,0) | AC7: =IF(AND(ISNUMBER(P7),ISNUMBER(Q7)),MIN(P7,Q7),IF(ISNUMBER(P7),P7,IF(ISNUMBER(Q7),Q7,0)))
A8: MEC-04 | B8: Estructura y eje Z | C8: Acople flexible 5 → 8 mm | D8: Aluminio | E8: Motor Z → husillo | F8: HTM | G8: 1 | H8: Obligatorio | I8: Creativo 3D | J8: 5 | K8: 1 | L8: Cotizar (estimado) | M8: 9.99 | N8: 5 | O8: 0.25 | P8: =IF(J8="","",ROUNDUP(G8/K8,0)*J8*(1-IF(ISNUMBER(SEARCH("Casa Rivas",I8)),DescCasaRivas,0))) | Q8: =IF(M8="","",ROUNDUP(G8/N8,0)*(M8*(1+TasaVentasEEUU)+O8*FleteLb*(1+IVA)+M8*(1+RecargoCIF)*IVA)) | R8: =IF(AND(ISNUMBER(P8),ISNUMBER(Q8)),IF(P8<=Q8,"Local","Amazon"),IF(ISNUMBER(P8),"Local",IF(ISNUMBER(Q8),"Amazon","—"))) | S8: Amazon | T8: =IF(S8="Amazon",IF(ISNUMBER(Q8),Q8,0),IF(ISNUMBER(P8),P8,0)) | U8: Por comprar | V8: =SUMIFS('Registro de gastos'!$F$10:$F$400,'Registro de gastos'!$B$10:$B$400,A8) | W8: =IF(OR(U8="Por comprar",U8="Cotizado"),MAX(T8-V8,0),0) | X8: =V8+W8 | Z8: https://www.amazon.com/dp/B07JL1QYLS | AB8: =IF(AND(S8="Amazon",ISNUMBER(M8),W8>0),ROUNDUP(G8/N8,0)*M8,0) | AC8: =IF(AND(ISNUMBER(P8),ISNUMBER(Q8)),MIN(P8,Q8),IF(ISNUMBER(P8),P8,IF(ISNUMBER(Q8),Q8,0)))
A9: MEC-05 | B9: Estructura y eje Z | C9: Base de madera o MDF 18–20 mm | D9: ≈ 30 × 25 cm | E9: Fijar la base del robot (12 agujeros) | F9: HTM | G9: 1 | H9: Recomendado | I9: Almacenes Vidrí | J9: 6 | K9: 1 | L9: Estimado | P9: =IF(J9="","",ROUNDUP(G9/K9,0)*J9*(1-IF(ISNUMBER(SEARCH("Casa Rivas",I9)),DescCasaRivas,0))) | Q9: =IF(M9="","",ROUNDUP(G9/N9,0)*(M9*(1+TasaVentasEEUU)+O9*FleteLb*(1+IVA)+M9*(1+RecargoCIF)*IVA)) | R9: =IF(AND(ISNUMBER(P9),ISNUMBER(Q9)),IF(P9<=Q9,"Local","Amazon"),IF(ISNUMBER(P9),"Local",IF(ISNUMBER(Q9),"Amazon","—"))) | S9: Local | T9: =IF(S9="Amazon",IF(ISNUMBER(Q9),Q9,0),IF(ISNUMBER(P9),P9,0)) | U9: Ya lo tenemos | V9: =SUMIFS('Registro de gastos'!$F$10:$F$400,'Registro de gastos'!$B$10:$B$400,A9) | W9: =IF(OR(U9="Por comprar",U9="Cotizado"),MAX(T9-V9,0),0) | X9: =V9+W9 | AA9: La consiguen sin costo. El artículo atornilla la base a madera de 20 mm y la sujeta a la mesa con prensas. | AB9: =IF(AND(S9="Amazon",ISNUMBER(M9),W9>0),ROUNDUP(G9/N9,0)*M9,0) | AC9: =IF(AND(ISNUMBER(P9),ISNUMBER(Q9)),MIN(P9,Q9),IF(ISNUMBER(P9),P9,IF(ISNUMBER(Q9),Q9,0)))
A10: ROD-01 | B10: Rodamientos | C10: Rodamiento axial 51108 | D10: 40 × 60 × 13 mm | E10: J1 (uno a cada lado de la base) | F10: HTM | G10: 2 | H10: Obligatorio | I10: CEROSA / RODASA / REPSA | J10: 6 | K10: 1 | L10: Cotizar (estimado) | M10: 9.99 | N10: 2 | O10: 0.45 | P10: =IF(J10="","",ROUNDUP(G10/K10,0)*J10*(1-IF(ISNUMBER(SEARCH("Casa Rivas",I10)),DescCasaRivas,0))) | Q10: =IF(M10="","",ROUNDUP(G10/N10,0)*(M10*(1+TasaVentasEEUU)+O10*FleteLb*(1+IVA)+M10*(1+RecargoCIF)*IVA)) | R10: =IF(AND(ISNUMBER(P10),ISNUMBER(Q10)),IF(P10<=Q10,"Local","Amazon"),IF(ISNUMBER(P10),"Local",IF(ISNUMBER(Q10),"Amazon","—"))) | S10: Amazon | T10: =IF(S10="Amazon",IF(ISNUMBER(Q10),Q10,0),IF(ISNUMBER(P10),P10,0)) | U10: Por comprar | V10: =SUMIFS('Registro de gastos'!$F$10:$F$400,'Registro de gastos'!$B$10:$B$400,A10) | W10: =IF(OR(U10="Por comprar",U10="Cotizado"),MAX(T10-V10,0),0) | X10: =V10+W10 | Z10: https://www.amazon.com/dp/B0FDKPGXQ4 | AA10: La lista del artículo dice 1, pero el ensamble usa 2. | AB10: =IF(AND(S10="Amazon",ISNUMBER(M10),W10>0),ROUNDUP(G10/N10,0)*M10,0) | AC10: =IF(AND(ISNUMBER(P10),ISNUMBER(Q10)),MIN(P10,Q10),IF(ISNUMBER(P10),P10,IF(ISNUMBER(Q10),Q10,0)))
A11: ROD-02 | B11: Rodamientos | C11: Rodamiento axial 51107 | D11: 35 × 52 × 12 mm | E11: J2 y J3 (2 por junta) | F11: HTM | G11: 4 | H11: Obligatorio | I11: CEROSA / RODASA / REPSA | J11: 5 | K11: 1 | L11: Cotizar (estimado) | M11: 10.99 | N11: 3 | O11: 0.45 | P11: =IF(J11="","",ROUNDUP(G11/K11,0)*J11*(1-IF(ISNUMBER(SEARCH("Casa Rivas",I11)),DescCasaRivas,0))) | Q11: =IF(M11="","",ROUNDUP(G11/N11,0)*(M11*(1+TasaVentasEEUU)+O11*FleteLb*(1+IVA)+M11*(1+RecargoCIF)*IVA)) | R11: =IF(AND(ISNUMBER(P11),ISNUMBER(Q11)),IF(P11<=Q11,"Local","Amazon"),IF(ISNUMBER(P11),"Local",IF(ISNUMBER(Q11),"Amazon","—"))) | S11: Amazon | T11: =IF(S11="Amazon",IF(ISNUMBER(Q11),Q11,0),IF(ISNUMBER(P11),P11,0)) | U11: Por comprar | V11: =SUMIFS('Registro de gastos'!$F$10:$F$400,'Registro de gastos'!$B$10:$B$400,A11) | W11: =IF(OR(U11="Por comprar",U11="Cotizado"),MAX(T11-V11,0),0) | X11: =V11+W11 | Z11: https://www.amazon.com/s?k=51107+thrust+ball+bearing | AA11: La lista del artículo pide 2 (solo J2); J3 usa el mismo esquema. Paquete de 3 en Amazon. | AB11: =IF(AND(S11="Amazon",ISNUMBER(M11),W11>0),ROUNDUP(G11/N11,0)*M11,0) | AC11: =IF(AND(ISNUMBER(P11),ISNUMBER(Q11)),MIN(P11,Q11),IF(ISNUMBER(P11),P11,IF(ISNUMBER(Q11),Q11,0)))
A12: ROD-03 | B12: Rodamientos | C12: Rodamiento radial 6807-2RS | D12: 35 × 47 × 7 mm (pared delgada) | E12: J1 | F12: HTM | G12: 1 | H12: Obligatorio | I12: CEROSA / RODASA / REPSA | J12: 5 | K12: 1 | L12: Cotizar (estimado) | M12: 7.29 | N12: 1 | O12: 0.1 | P12: =IF(J12="","",ROUNDUP(G12/K12,0)*J12*(1-IF(ISNUMBER(SEARCH("Casa Rivas",I12)),DescCasaRivas,0))) | Q12: =IF(M12="","",ROUNDUP(G12/N12,0)*(M12*(1+TasaVentasEEUU)+O12*FleteLb*(1+IVA)+M12*(1+RecargoCIF)*IVA)) | R12: =IF(AND(ISNUMBER(P12),ISNUMBER(Q12)),IF(P12<=Q12,"Local","Amazon"),IF(ISNUMBER(P12),"Local",IF(ISNUMBER(Q12),"Amazon","—"))) | S12: Local | T12: =IF(S12="Amazon",IF(ISNUMBER(Q12),Q12,0),IF(ISNUMBER(P12),P12,0)) | U12: Por comprar | V12: =SUMIFS('Registro de gastos'!$F$10:$F$400,'Registro de gastos'!$B$10:$B$400,A12) | W12: =IF(OR(U12="Por comprar",U12="Cotizado"),MAX(T12-V12,0),0) | X12: =V12+W12 | Z12: https://www.amazon.com/dp/B07RP6RDYL | AA12: No aparece en la lista del artículo, pero el texto lo instala primero en la base. | AB12: =IF(AND(S12="Amazon",ISNUMBER(M12),W12>0),ROUNDUP(G12/N12,0)*M12,0) | AC12: =IF(AND(ISNUMBER(P12),ISNUMBER(Q12)),MIN(P12,Q12),IF(ISNUMBER(P12),P12,IF(ISNUMBER(Q12),Q12,0)))
A13: ROD-04 | B13: Rodamientos | C13: Rodamiento radial 6806-2RS (61806) | D13: 30 × 42 × 7 mm (pared delgada) | E13: J2 y J3 | F13: HTM | G13: 2 | H13: Obligatorio | I13: CEROSA / RODASA / REPSA | J13: 4.5 | K13: 1 | L13: Cotizar (estimado) | M13: 13.99 | N13: 10 | O13: 0.5 | P13: =IF(J13="","",ROUNDUP(G13/K13,0)*J13*(1-IF(ISNUMBER(SEARCH("Casa Rivas",I13)),DescCasaRivas,0))) | Q13: =IF(M13="","",ROUNDUP(G13/N13,0)*(M13*(1+TasaVentasEEUU)+O13*FleteLb*(1+IVA)+M13*(1+RecargoCIF)*IVA)) | R13: =IF(AND(ISNUMBER(P13),ISNUMBER(Q13)),IF(P13<=Q13,"Local","Amazon"),IF(ISNUMBER(P13),"Local",IF(ISNUMBER(Q13),"Amazon","—"))) | S13: Local | T13: =IF(S13="Amazon",IF(ISNUMBER(Q13),Q13,0),IF(ISNUMBER(P13),P13,0)) | U13: Por comprar | V13: =SUMIFS('Registro de gastos'!$F$10:$F$400,'Registro de gastos'!$B$10:$B$400,A13) | W13: =IF(OR(U13="Por comprar",U13="Cotizado"),MAX(T13-V13,0),0) | X13: =V13+W13 | Z13: https://www.amazon.com/dp/B09D33QXFL | AA13: Amazon solo lo vende en paquete de 10. | AB13: =IF(AND(S13="Amazon",ISNUMBER(M13),W13>0),ROUNDUP(G13/N13,0)*M13,0) | AC13: =IF(AND(ISNUMBER(P13),ISNUMBER(Q13)),MIN(P13,Q13),IF(ISNUMBER(P13),P13,IF(ISNUMBER(Q13),Q13,0)))
A14: ROD-05 | B14: Rodamientos | C14: Rodamiento 608ZZ | D14: 8 × 22 × 7 mm | E14: Poleas intermedias de J1 y J2 (2 c/u) + husillo | F14: HTM | G14: 5 | H14: Obligatorio | I14: CEROSA / REPSA | J14: 1.25 | K14: 1 | L14: Estimado (hay en el país) | M14: 5.19 | N14: 10 | O14: 0.35 | P14: =IF(J14="","",ROUNDUP(G14/K14,0)*J14*(1-IF(ISNUMBER(SEARCH("Casa Rivas",I14)),DescCasaRivas,0))) | Q14: =IF(M14="","",ROUNDUP(G14/N14,0)*(M14*(1+TasaVentasEEUU)+O14*FleteLb*(1+IVA)+M14*(1+RecargoCIF)*IVA)) | R14: =IF(AND(ISNUMBER(P14),ISNUMBER(Q14)),IF(P14<=Q14,"Local","Amazon"),IF(ISNUMBER(P14),"Local",IF(ISNUMBER(Q14),"Amazon","—"))) | S14: Local | T14: =IF(S14="Amazon",IF(ISNUMBER(Q14),Q14,0),IF(ISNUMBER(P14),P14,0)) | U14: Por comprar | V14: =SUMIFS('Registro de gastos'!$F$10:$F$400,'Registro de gastos'!$B$10:$B$400,A14) | W14: =IF(OR(U14="Por comprar",U14="Cotizado"),MAX(T14-V14,0),0) | X14: =V14+W14 | Z14: https://www.amazon.com/dp/B0GYVYQKQ4 | AB14: =IF(AND(S14="Amazon",ISNUMBER(M14),W14>0),ROUNDUP(G14/N14,0)*M14,0) | AC14: =IF(AND(ISNUMBER(P14),ISNUMBER(Q14)),MIN(P14,Q14),IF(ISNUMBER(P14),P14,IF(ISNUMBER(Q14),Q14,0)))
A15: TRA-01 | B15: Transmisión | C15: Correa GT2 cerrada 200 mm | D15: Ancho 6 mm, paso 2 mm | E15: J1 etapa 1 (motor → 80 dientes) | F15: HTM | G15: 1 | H15: Obligatorio | I15: Creativo 3D | J15: 4 | K15: 1 | L15: Cotizar (estimado) | M15: 6.92 | N15: 5 | O15: 0.1 | P15: =IF(J15="","",ROUNDUP(G15/K15,0)*J15*(1-IF(ISNUMBER(SEARCH("Casa Rivas",I15)),DescCasaRivas,0))) | Q15: =IF(M15="","",ROUNDUP(G15/N15,0)*(M15*(1+TasaVentasEEUU)+O15*FleteLb*(1+IVA)+M15*(1+RecargoCIF)*IVA)) | R15: =IF(AND(ISNUMBER(P15),ISNUMBER(Q15)),IF(P15<=Q15,"Local","Amazon"),IF(ISNUMBER(P15),"Local",IF(ISNUMBER(Q15),"Amazon","—"))) | S15: Amazon | T15: =IF(S15="Amazon",IF(ISNUMBER(Q15),Q15,0),IF(ISNUMBER(P15),P15,0)) | U15: Por comprar | V15: =SUMIFS('Registro de gastos'!$F$10:$F$400,'Registro de gastos'!$B$10:$B$400,A15) | W15: =IF(OR(U15="Por comprar",U15="Cotizado"),MAX(T15-V15,0),0) | X15: =V15+W15 | Z15: https://www.amazon.com/dp/B0FRDL4X1Z | AB15: =IF(AND(S15="Amazon",ISNUMBER(M15),W15>0),ROUNDUP(G15/N15,0)*M15,0) | AC15: =IF(AND(ISNUMBER(P15),ISNUMBER(Q15)),MIN(P15,Q15),IF(ISNUMBER(P15),P15,IF(ISNUMBER(Q15),Q15,0)))
A16: TRA-02 | B16: Transmisión | C16: Correa GT2 cerrada 300 mm | D16: Ancho 6 mm, paso 2 mm | E16: J1 etapa 2 y J2 etapa 2 | F16: HTM | G16: 2 | H16: Obligatorio | I16: Creativo 3D | J16: 4 | K16: 1 | L16: Cotizar (estimado) | M16: 8.79 | N16: 4 | O16: 0.1 | P16: =IF(J16="","",ROUNDUP(G16/K16,0)*J16*(1-IF(ISNUMBER(SEARCH("Casa Rivas",I16)),DescCasaRivas,0))) | Q16: =IF(M16="","",ROUNDUP(G16/N16,0)*(M16*(1+TasaVentasEEUU)+O16*FleteLb*(1+IVA)+M16*(1+RecargoCIF)*IVA)) | R16: =IF(AND(ISNUMBER(P16),ISNUMBER(Q16)),IF(P16<=Q16,"Local","Amazon"),IF(ISNUMBER(P16),"Local",IF(ISNUMBER(Q16),"Amazon","—"))) | S16: Amazon | T16: =IF(S16="Amazon",IF(ISNUMBER(Q16),Q16,0),IF(ISNUMBER(P16),P16,0)) | U16: Por comprar | V16: =SUMIFS('Registro de gastos'!$F$10:$F$400,'Registro de gastos'!$B$10:$B$400,A16) | W16: =IF(OR(U16="Por comprar",U16="Cotizado"),MAX(T16-V16,0),0) | X16: =V16+W16 | Z16: https://www.amazon.com/dp/B0CN41SWMZ | AB16: =IF(AND(S16="Amazon",ISNUMBER(M16),W16>0),ROUNDUP(G16/N16,0)*M16,0) | AC16: =IF(AND(ISNUMBER(P16),ISNUMBER(Q16)),MIN(P16,Q16),IF(ISNUMBER(P16),P16,IF(ISNUMBER(Q16),Q16,0)))
A17: TRA-03 | B17: Transmisión | C17: Correa GT2 cerrada 400 mm | D17: Ancho 6 mm, paso 2 mm | E17: J2 etapa 1 y J3 | F17: HTM | G17: 2 | H17: Obligatorio | I17: Creativo 3D | J17: 4.5 | K17: 1 | L17: Cotizar (estimado) | M17: 9.21 | N17: 5 | O17: 0.1 | P17: =IF(J17="","",ROUNDUP(G17/K17,0)*J17*(1-IF(ISNUMBER(SEARCH("Casa Rivas",I17)),DescCasaRivas,0))) | Q17: =IF(M17="","",ROUNDUP(G17/N17,0)*(M17*(1+TasaVentasEEUU)+O17*FleteLb*(1+IVA)+M17*(1+RecargoCIF)*IVA)) | R17: =IF(AND(ISNUMBER(P17),ISNUMBER(Q17)),IF(P17<=Q17,"Local","Amazon"),IF(ISNUMBER(P17),"Local",IF(ISNUMBER(Q17),"Amazon","—"))) | S17: Amazon | T17: =IF(S17="Amazon",IF(ISNUMBER(Q17),Q17,0),IF(ISNUMBER(P17),P17,0)) | U17: Por comprar | V17: =SUMIFS('Registro de gastos'!$F$10:$F$400,'Registro de gastos'!$B$10:$B$400,A17) | W17: =IF(OR(U17="Por comprar",U17="Cotizado"),MAX(T17-V17,0),0) | X17: =V17+W17 | Z17: https://www.amazon.com/dp/B0FRD6MX8J | AA17: Las poleas GT2 (110, 92, 90, 22-80, 23-80 y 20 dientes) se imprimen: ver hoja Impresión 3D. | AB17: =IF(AND(S17="Amazon",ISNUMBER(M17),W17>0),ROUNDUP(G17/N17,0)*M17,0) | AC17: =IF(AND(ISNUMBER(P17),ISNUMBER(Q17)),MIN(P17,Q17),IF(ISNUMBER(P17),P17,IF(ISNUMBER(Q17),Q17,0)))
A18: ELE-01 | B18: Motores y electrónica | C18: Motor paso a paso NEMA 17, 40 mm | D18: 45 N·cm, 2 A, 1.8°, 4 cables (17HS4401) | E18: J1, J2 y Z | F18: HTM | G18: 3 | H18: Obligatorio | I18: Electrónica 2001 (código 04-355) | J18: 12 | K18: 1 | L18: Verificado en línea 06-oct-2026 | M18: 13.99 | N18: 1 | O18: 0.75 | P18: =IF(J18="","",ROUNDUP(G18/K18,0)*J18*(1-IF(ISNUMBER(SEARCH("Casa Rivas",I18)),DescCasaRivas,0))) | Q18: =IF(M18="","",ROUNDUP(G18/N18,0)*(M18*(1+TasaVentasEEUU)+O18*FleteLb*(1+IVA)+M18*(1+RecargoCIF)*IVA)) | R18: =IF(AND(ISNUMBER(P18),ISNUMBER(Q18)),IF(P18<=Q18,"Local","Amazon"),IF(ISNUMBER(P18),"Local",IF(ISNUMBER(Q18),"Amazon","—"))) | S18: Local | T18: =IF(S18="Amazon",IF(ISNUMBER(Q18),Q18,0),IF(ISNUMBER(P18),P18,0)) | U18: Ya lo tenemos | V18: =SUMIFS('Registro de gastos'!$F$10:$F$400,'Registro de gastos'!$B$10:$B$400,A18) | W18: =IF(OR(U18="Por comprar",U18="Cotizado"),MAX(T18-V18,0),0) | X18: =V18+W18 | Z18: https://www.amazon.com/dp/B00PNEQI7W | AA18: Prestados. Si usan el NEMA corto también en J2 (varillas de 240 mm), bajar a 2 y subir ELE-02 a 2. Confirmar que trae cable. | AB18: =IF(AND(S18="Amazon",ISNUMBER(M18),W18>0),ROUNDUP(G18/N18,0)*M18,0) | AC18: =IF(AND(ISNUMBER(P18),ISNUMBER(Q18)),MIN(P18,Q18),IF(ISNUMBER(P18),P18,IF(ISNUMBER(Q18),Q18,0)))
A19: ELE-02 | B19: Motores y electrónica | C19: Motor NEMA 17 corto (pancake) | D19: ≈ 23 mm, 17 N·cm, 1 A | E19: J3 (aligera el brazo 2) | F19: HTM | G19: 1 | H19: Obligatorio | I19: Electrónica 2001 (preguntar) | M19: 10.5 | N19: 1 | O19: 0.45 | P19: =IF(J19="","",ROUNDUP(G19/K19,0)*J19*(1-IF(ISNUMBER(SEARCH("Casa Rivas",I19)),DescCasaRivas,0))) | Q19: =IF(M19="","",ROUNDUP(G19/N19,0)*(M19*(1+TasaVentasEEUU)+O19*FleteLb*(1+IVA)+M19*(1+RecargoCIF)*IVA)) | R19: =IF(AND(ISNUMBER(P19),ISNUMBER(Q19)),IF(P19<=Q19,"Local","Amazon"),IF(ISNUMBER(P19),"Local",IF(ISNUMBER(Q19),"Amazon","—"))) | S19: Amazon | T19: =IF(S19="Amazon",IF(ISNUMBER(Q19),Q19,0),IF(ISNUMBER(P19),P19,0)) | U19: Ya lo tenemos | V19: =SUMIFS('Registro de gastos'!$F$10:$F$400,'Registro de gastos'!$B$10:$B$400,A19) | W19: =IF(OR(U19="Por comprar",U19="Cotizado"),MAX(T19-V19,0),0) | X19: =V19+W19 | Z19: https://www.amazon.com/dp/B0B93PNYCP | AA19: Prestado: si es de 40 mm también sirve en J3 (pesa más en el brazo 2). El artículo usa un NEMA 17 de 24 mm en J3. Si no lo consiguen, sirve uno de 40 mm (más peso en el brazo 2). | AB19: =IF(AND(S19="Amazon",ISNUMBER(M19),W19>0),ROUNDUP(G19/N19,0)*M19,0) | AC19: =IF(AND(ISNUMBER(P19),ISNUMBER(Q19)),MIN(P19,Q19),IF(ISNUMBER(P19),P19,IF(ISNUMBER(Q19),Q19,0)))
A20: ELE-03 | B20: Motores y electrónica | C20: CNC Shield V3 + 4 drivers A4988 | D20: Con disipadores y jumpers | E20: Control de los 4 motores | F20: HTM | G20: 1 | H20: Obligatorio | I20: ArduStore SV / Casa Rivas (preguntar) | J20: 18 | K20: 1 | L20: Cotizar (estimado) | M20: 9.99 | N20: 1 | O20: 0.25 | P20: =IF(J20="","",ROUNDUP(G20/K20,0)*J20*(1-IF(ISNUMBER(SEARCH("Casa Rivas",I20)),DescCasaRivas,0))) | Q20: =IF(M20="","",ROUNDUP(G20/N20,0)*(M20*(1+TasaVentasEEUU)+O20*FleteLb*(1+IVA)+M20*(1+RecargoCIF)*IVA)) | R20: =IF(AND(ISNUMBER(P20),ISNUMBER(Q20)),IF(P20<=Q20,"Local","Amazon"),IF(ISNUMBER(P20),"Local",IF(ISNUMBER(Q20),"Amazon","—"))) | S20: Amazon | T20: =IF(S20="Amazon",IF(ISNUMBER(Q20),Q20,0),IF(ISNUMBER(P20),P20,0)) | U20: Ya lo tenemos | V20: =SUMIFS('Registro de gastos'!$F$10:$F$400,'Registro de gastos'!$B$10:$B$400,A20) | W20: =IF(OR(U20="Por comprar",U20="Cotizado"),MAX(T20-V20,0),0) | X20: =V20+W20 | Z20: https://www.amazon.com/dp/B07TT3C3HB | AA20: Jumpers en ¼ de paso, como en el artículo. | AB20: =IF(AND(S20="Amazon",ISNUMBER(M20),W20>0),ROUNDUP(G20/N20,0)*M20,0) | AC20: =IF(AND(ISNUMBER(P20),ISNUMBER(Q20)),MIN(P20,Q20),IF(ISNUMBER(P20),P20,IF(ISNUMBER(Q20),Q20,0)))
A21: ELE-04 | B21: Motores y electrónica | C21: Drivers A4988 de repuesto | D21: Paquete de 5 con disipador | E21: Reemplazo si se quema uno | F21: MathBot | G21: 5 | H21: Opcional | M21: 10.19 | N21: 5 | O21: 0.1 | P21: =IF(J21="","",ROUNDUP(G21/K21,0)*J21*(1-IF(ISNUMBER(SEARCH("Casa Rivas",I21)),DescCasaRivas,0))) | Q21: =IF(M21="","",ROUNDUP(G21/N21,0)*(M21*(1+TasaVentasEEUU)+O21*FleteLb*(1+IVA)+M21*(1+RecargoCIF)*IVA)) | R21: =IF(AND(ISNUMBER(P21),ISNUMBER(Q21)),IF(P21<=Q21,"Local","Amazon"),IF(ISNUMBER(P21),"Local",IF(ISNUMBER(Q21),"Amazon","—"))) | S21: Amazon | T21: =IF(S21="Amazon",IF(ISNUMBER(Q21),Q21,0),IF(ISNUMBER(P21),P21,0)) | U21: No comprar | V21: =SUMIFS('Registro de gastos'!$F$10:$F$400,'Registro de gastos'!$B$10:$B$400,A21) | W21: =IF(OR(U21="Por comprar",U21="Cotizado"),MAX(T21-V21,0),0) | X21: =V21+W21 | Z21: https://www.amazon.com/dp/B07BND65C8 | AB21: =IF(AND(S21="Amazon",ISNUMBER(M21),W21>0),ROUNDUP(G21/N21,0)*M21,0) | AC21: =IF(AND(ISNUMBER(P21),ISNUMBER(Q21)),MIN(P21,Q21),IF(ISNUMBER(P21),P21,IF(ISNUMBER(Q21),Q21,0)))
A22: ELE-05 | B22: Motores y electrónica | C22: Arduino MEGA 2560 R3 (compatible) | D22: ATmega2560 | E22: Cerebro del robot | F22: MathBot | G22: 1 | H22: Obligatorio | I22: Electrónica 2001 / Casa Rivas | L22: Cotizar | O22: 0.2 | P22: =IF(J22="","",ROUNDUP(G22/K22,0)*J22*(1-IF(ISNUMBER(SEARCH("Casa Rivas",I22)),DescCasaRivas,0))) | Q22: =IF(M22="","",ROUNDUP(G22/N22,0)*(M22*(1+TasaVentasEEUU)+O22*FleteLb*(1+IVA)+M22*(1+RecargoCIF)*IVA)) | R22: =IF(AND(ISNUMBER(P22),ISNUMBER(Q22)),IF(P22<=Q22,"Local","Amazon"),IF(ISNUMBER(P22),"Local",IF(ISNUMBER(Q22),"Amazon","—"))) | S22: Local | T22: =IF(S22="Amazon",IF(ISNUMBER(Q22),Q22,0),IF(ISNUMBER(P22),P22,0)) | U22: Ya lo tenemos | V22: =SUMIFS('Registro de gastos'!$F$10:$F$400,'Registro de gastos'!$B$10:$B$400,A22) | W22: =IF(OR(U22="Por comprar",U22="Cotizado"),MAX(T22-V22,0),0) | X22: =V22+W22 | Z22: https://www.amazon.com/s?k=Arduino+Mega+2560+R3 | AA22: Prestado: confirmar que sea un MEGA 2560 (un UNO no tiene los pines del cabezal). El firmware (firmware/mathbot_mega) usa pines que el UNO no tiene: D22 sensor, D24 electroimán, D44 servo. La CNC Shield V3 encaja igual que sobre el UNO. | AB22: =IF(AND(S22="Amazon",ISNUMBER(M22),W22>0),ROUNDUP(G22/N22,0)*M22,0) | AC22: =IF(AND(ISNUMBER(P22),ISNUMBER(Q22)),MIN(P22,Q22),IF(ISNUMBER(P22),P22,IF(ISNUMBER(Q22),Q22,0)))
A23: ELE-06 | B23: Motores y electrónica | C23: Fuente de 12 V | D23: Mín. 4 A; el artículo sugiere 6 A | E23: Alimentación general | F23: HTM | G23: 1 | H23: Obligatorio | I23: Steren (ELI-1260, 12 V 5 A) | J23: 25 | K23: 1 | L23: Verificado en línea 06-oct-2026 | M23: 15.99 | N23: 1 | O23: 0.9 | P23: =IF(J23="","",ROUNDUP(G23/K23,0)*J23*(1-IF(ISNUMBER(SEARCH("Casa Rivas",I23)),DescCasaRivas,0))) | Q23: =IF(M23="","",ROUNDUP(G23/N23,0)*(M23*(1+TasaVentasEEUU)+O23*FleteLb*(1+IVA)+M23*(1+RecargoCIF)*IVA)) | R23: =IF(AND(ISNUMBER(P23),ISNUMBER(Q23)),IF(P23<=Q23,"Local","Amazon"),IF(ISNUMBER(P23),"Local",IF(ISNUMBER(Q23),"Amazon","—"))) | S23: Amazon | T23: =IF(S23="Amazon",IF(ISNUMBER(Q23),Q23,0),IF(ISNUMBER(P23),P23,0)) | U23: Ya lo tenemos | V23: =SUMIFS('Registro de gastos'!$F$10:$F$400,'Registro de gastos'!$B$10:$B$400,A23) | W23: =IF(OR(U23="Por comprar",U23="Cotizado"),MAX(T23-V23,0),0) | X23: =V23+W23 | Z23: https://www.amazon.com/dp/B082PCR5YS | AA23: Usarán una fuente propia: confirmar que da 12 V y al menos 4 A (mejor 5 A con electroimán y servo). Amazon: ALITOVE 12 V 6 A. Steren también tiene la ELI-F3012 (12 V 30 A, USD 27.99), que es abierta y hay que cablear a 120 V. | AB23: =IF(AND(S23="Amazon",ISNUMBER(M23),W23>0),ROUNDUP(G23/N23,0)*M23,0) | AC23: =IF(AND(ISNUMBER(P23),ISNUMBER(Q23)),MIN(P23,Q23),IF(ISNUMBER(P23),P23,IF(ISNUMBER(Q23),Q23,0)))
A24: ELE-07 | B24: Motores y electrónica | C24: Final de carrera (micro switch con palanca) | E24: Homing de J1, J2, J3 y Z | F24: HTM | G24: 4 | H24: Obligatorio | I24: Steren (SS0501A) | J24: 0.75 | K24: 1 | L24: Verificado en línea 06-oct-2026 | M24: 5.99 | N24: 10 | O24: 0.15 | P24: =IF(J24="","",ROUNDUP(G24/K24,0)*J24*(1-IF(ISNUMBER(SEARCH("Casa Rivas",I24)),DescCasaRivas,0))) | Q24: =IF(M24="","",ROUNDUP(G24/N24,0)*(M24*(1+TasaVentasEEUU)+O24*FleteLb*(1+IVA)+M24*(1+RecargoCIF)*IVA)) | R24: =IF(AND(ISNUMBER(P24),ISNUMBER(Q24)),IF(P24<=Q24,"Local","Amazon"),IF(ISNUMBER(P24),"Local",IF(ISNUMBER(Q24),"Amazon","—"))) | S24: Local | T24: =IF(S24="Amazon",IF(ISNUMBER(Q24),Q24,0),IF(ISNUMBER(P24),P24,0)) | U24: Por comprar | V24: =SUMIFS('Registro de gastos'!$F$10:$F$400,'Registro de gastos'!$B$10:$B$400,A24) | W24: =IF(OR(U24="Por comprar",U24="Cotizado"),MAX(T24-V24,0),0) | X24: =V24+W24 | Z24: https://www.amazon.com/dp/B07X142VGC | AB24: =IF(AND(S24="Amazon",ISNUMBER(M24),W24>0),ROUNDUP(G24/N24,0)*M24,0) | AC24: =IF(AND(ISNUMBER(P24),ISNUMBER(Q24)),MIN(P24,Q24),IF(ISNUMBER(P24),P24,IF(ISNUMBER(Q24),Q24,0)))
A25: ELE-08 | B25: Motores y electrónica | C25: Cables de motor de 1 m | D25: XH2.54 de 4 pines, paquete de 4 | E25: Llevar los motores hasta la CNC Shield | F25: HTM | G25: 4 | H25: Recomendado | M25: 7.99 | N25: 4 | O25: 0.3 | P25: =IF(J25="","",ROUNDUP(G25/K25,0)*J25*(1-IF(ISNUMBER(SEARCH("Casa Rivas",I25)),DescCasaRivas,0))) | Q25: =IF(M25="","",ROUNDUP(G25/N25,0)*(M25*(1+TasaVentasEEUU)+O25*FleteLb*(1+IVA)+M25*(1+RecargoCIF)*IVA)) | R25: =IF(AND(ISNUMBER(P25),ISNUMBER(Q25)),IF(P25<=Q25,"Local","Amazon"),IF(ISNUMBER(P25),"Local",IF(ISNUMBER(Q25),"Amazon","—"))) | S25: Amazon | T25: =IF(S25="Amazon",IF(ISNUMBER(Q25),Q25,0),IF(ISNUMBER(P25),P25,0)) | U25: Por comprar | V25: =SUMIFS('Registro de gastos'!$F$10:$F$400,'Registro de gastos'!$B$10:$B$400,A25) | W25: =IF(OR(U25="Por comprar",U25="Cotizado"),MAX(T25-V25,0),0) | X25: =V25+W25 | Z25: https://www.amazon.com/dp/B0GYP4NNBR | AA25: Los NEMA suelen traer cable corto; J2 y J3 necesitan ≈1 m por los ejes huecos. | AB25: =IF(AND(S25="Amazon",ISNUMBER(M25),W25>0),ROUNDUP(G25/N25,0)*M25,0) | AC25: =IF(AND(ISNUMBER(P25),ISNUMBER(Q25)),MIN(P25,Q25),IF(ISNUMBER(P25),P25,IF(ISNUMBER(Q25),Q25,0)))
A26: ELE-09 | B26: Motores y electrónica | C26: Cables Dupont (80 pzs, 15 cm) | E26: Pruebas y conexiones del cabezal | F26: MathBot | G26: 1 | H26: Recomendado | I26: Steren (ARD-310) | J26: 3.99 | K26: 1 | L26: Verificado en línea 06-oct-2026 | P26: =IF(J26="","",ROUNDUP(G26/K26,0)*J26*(1-IF(ISNUMBER(SEARCH("Casa Rivas",I26)),DescCasaRivas,0))) | Q26: =IF(M26="","",ROUNDUP(G26/N26,0)*(M26*(1+TasaVentasEEUU)+O26*FleteLb*(1+IVA)+M26*(1+RecargoCIF)*IVA)) | R26: =IF(AND(ISNUMBER(P26),ISNUMBER(Q26)),IF(P26<=Q26,"Local","Amazon"),IF(ISNUMBER(P26),"Local",IF(ISNUMBER(Q26),"Amazon","—"))) | S26: Local | T26: =IF(S26="Amazon",IF(ISNUMBER(Q26),Q26,0),IF(ISNUMBER(P26),P26,0)) | U26: Ya lo tenemos | V26: =SUMIFS('Registro de gastos'!$F$10:$F$400,'Registro de gastos'!$B$10:$B$400,A26) | W26: =IF(OR(U26="Por comprar",U26="Cotizado"),MAX(T26-V26,0),0) | X26: =V26+W26 | AA26: Tienen jumpers de sobra. | AB26: =IF(AND(S26="Amazon",ISNUMBER(M26),W26>0),ROUNDUP(G26/N26,0)*M26,0) | AC26: =IF(AND(ISNUMBER(P26),ISNUMBER(Q26)),MIN(P26,Q26),IF(ISNUMBER(P26),P26,IF(ISNUMBER(Q26),Q26,0)))
A27: ELE-10 | B27: Motores y electrónica | C27: Jack DC hembra + bornera de potencia | D27: 5.5 × 2.1 mm | E27: Entrada de 12 V a la CNC Shield | F27: HTM | G27: 1 | H27: Obligatorio | I27: Casa Rivas | J27: 1.5 | K27: 1 | L27: Estimado | P27: =IF(J27="","",ROUNDUP(G27/K27,0)*J27*(1-IF(ISNUMBER(SEARCH("Casa Rivas",I27)),DescCasaRivas,0))) | Q27: =IF(M27="","",ROUNDUP(G27/N27,0)*(M27*(1+TasaVentasEEUU)+O27*FleteLb*(1+IVA)+M27*(1+RecargoCIF)*IVA)) | R27: =IF(AND(ISNUMBER(P27),ISNUMBER(Q27)),IF(P27<=Q27,"Local","Amazon"),IF(ISNUMBER(P27),"Local",IF(ISNUMBER(Q27),"Amazon","—"))) | S27: Local | T27: =IF(S27="Amazon",IF(ISNUMBER(Q27),Q27,0),IF(ISNUMBER(P27),P27,0)) | U27: Por comprar | V27: =SUMIFS('Registro de gastos'!$F$10:$F$400,'Registro de gastos'!$B$10:$B$400,A27) | W27: =IF(OR(U27="Por comprar",U27="Cotizado"),MAX(T27-V27,0),0) | X27: =V27+W27 | AB27: =IF(AND(S27="Amazon",ISNUMBER(M27),W27>0),ROUNDUP(G27/N27,0)*M27,0) | AC27: =IF(AND(ISNUMBER(P27),ISNUMBER(Q27)),MIN(P27,Q27),IF(ISNUMBER(P27),P27,IF(ISNUMBER(Q27),Q27,0)))
A28: CAB-01 | B28: Cabezal de disco | C28: Electroimán 12 V P20/15 | D28: Ø20 × 15 mm, 2.5 kgf, ≈0.25 A | E28: Recoger las piezas metálicas | F28: MathBot | G28: 1 | H28: Obligatorio | I28: No se encontró en el país | M28: 6.59 | N28: 1 | O28: 0.15 | P28: =IF(J28="","",ROUNDUP(G28/K28,0)*J28*(1-IF(ISNUMBER(SEARCH("Casa Rivas",I28)),DescCasaRivas,0))) | Q28: =IF(M28="","",ROUNDUP(G28/N28,0)*(M28*(1+TasaVentasEEUU)+O28*FleteLb*(1+IVA)+M28*(1+RecargoCIF)*IVA)) | R28: =IF(AND(ISNUMBER(P28),ISNUMBER(Q28)),IF(P28<=Q28,"Local","Amazon"),IF(ISNUMBER(P28),"Local",IF(ISNUMBER(Q28),"Amazon","—"))) | S28: Amazon | T28: =IF(S28="Amazon",IF(ISNUMBER(Q28),Q28,0),IF(ISNUMBER(P28),P28,0)) | U28: Por comprar | V28: =SUMIFS('Registro de gastos'!$F$10:$F$400,'Registro de gastos'!$B$10:$B$400,A28) | W28: =IF(OR(U28="Por comprar",U28="Cotizado"),MAX(T28-V28,0),0) | X28: =V28+W28 | Z28: https://www.amazon.com/dp/B078KBJNFC | AB28: =IF(AND(S28="Amazon",ISNUMBER(M28),W28>0),ROUNDUP(G28/N28,0)*M28,0) | AC28: =IF(AND(ISNUMBER(P28),ISNUMBER(Q28)),MIN(P28,Q28),IF(ISNUMBER(P28),P28,IF(ISNUMBER(Q28),Q28,0)))
A29: CAB-02 | B29: Cabezal de disco | C29: Sensor inductivo LJ12A3-4-Z/BX | D29: M12, NPN NA, 6–36 V, detecta a 4 mm | E29: Detectar metal | F29: MathBot | G29: 1 | H29: Obligatorio | I29: Prestelectro / Intek (industrial) | J29: 35 | K29: 1 | L29: Estimado (USD 25–60) | M29: 9.99 | N29: 3 | O29: 0.35 | P29: =IF(J29="","",ROUNDUP(G29/K29,0)*J29*(1-IF(ISNUMBER(SEARCH("Casa Rivas",I29)),DescCasaRivas,0))) | Q29: =IF(M29="","",ROUNDUP(G29/N29,0)*(M29*(1+TasaVentasEEUU)+O29*FleteLb*(1+IVA)+M29*(1+RecargoCIF)*IVA)) | R29: =IF(AND(ISNUMBER(P29),ISNUMBER(Q29)),IF(P29<=Q29,"Local","Amazon"),IF(ISNUMBER(P29),"Local",IF(ISNUMBER(Q29),"Amazon","—"))) | S29: Amazon | T29: =IF(S29="Amazon",IF(ISNUMBER(Q29),Q29,0),IF(ISNUMBER(P29),P29,0)) | U29: Por comprar | V29: =SUMIFS('Registro de gastos'!$F$10:$F$400,'Registro de gastos'!$B$10:$B$400,A29) | W29: =IF(OR(U29="Por comprar",U29="Cotizado"),MAX(T29-V29,0),0) | X29: =V29+W29 | Z29: https://www.amazon.com/s?k=LJ12A3-4-Z%2FBX | AA29: Paquete de 3: quedan 2 de repuesto. Uno individual (DEVMO, B07TMKTZ9L) cuesta USD 12.99. | AB29: =IF(AND(S29="Amazon",ISNUMBER(M29),W29>0),ROUNDUP(G29/N29,0)*M29,0) | AC29: =IF(AND(ISNUMBER(P29),ISNUMBER(Q29)),MIN(P29,Q29),IF(ISNUMBER(P29),P29,IF(ISNUMBER(Q29),Q29,0)))
A30: CAB-03 | B30: Cabezal de disco | C30: Micro servo SG90 / MG90S | E30: Levantar el plumón 18 mm | F30: MathBot | G30: 1 | H30: Obligatorio | I30: Casa Rivas | J30: 4 | K30: 1 | L30: Estimado (hay en el país) | M30: 8.88 | N30: 2 | O30: 0.15 | P30: =IF(J30="","",ROUNDUP(G30/K30,0)*J30*(1-IF(ISNUMBER(SEARCH("Casa Rivas",I30)),DescCasaRivas,0))) | Q30: =IF(M30="","",ROUNDUP(G30/N30,0)*(M30*(1+TasaVentasEEUU)+O30*FleteLb*(1+IVA)+M30*(1+RecargoCIF)*IVA)) | R30: =IF(AND(ISNUMBER(P30),ISNUMBER(Q30)),IF(P30<=Q30,"Local","Amazon"),IF(ISNUMBER(P30),"Local",IF(ISNUMBER(Q30),"Amazon","—"))) | S30: Local | T30: =IF(S30="Amazon",IF(ISNUMBER(Q30),Q30,0),IF(ISNUMBER(P30),P30,0)) | U30: Por comprar | V30: =SUMIFS('Registro de gastos'!$F$10:$F$400,'Registro de gastos'!$B$10:$B$400,A30) | W30: =IF(OR(U30="Por comprar",U30="Cotizado"),MAX(T30-V30,0),0) | X30: =V30+W30 | Z30: https://www.amazon.com/s?k=MG90S+metal+gear+2+pack | AB30: =IF(AND(S30="Amazon",ISNUMBER(M30),W30>0),ROUNDUP(G30/N30,0)*M30,0) | AC30: =IF(AND(ISNUMBER(P30),ISNUMBER(Q30)),MIN(P30,Q30),IF(ISNUMBER(P30),P30,IF(ISNUMBER(Q30),Q30,0)))
A31: CAB-04 | B31: Cabezal de disco | C31: Plumón Sharpie punta fina | D31: Negro | E31: Trazar la curva paramétrica | F31: MathBot | G31: 2 | H31: Obligatorio | I31: Librería o supermercado | J31: 1.5 | K31: 1 | L31: Estimado | M31: 1.97 | N31: 2 | O31: 0.05 | P31: =IF(J31="","",ROUNDUP(G31/K31,0)*J31*(1-IF(ISNUMBER(SEARCH("Casa Rivas",I31)),DescCasaRivas,0))) | Q31: =IF(M31="","",ROUNDUP(G31/N31,0)*(M31*(1+TasaVentasEEUU)+O31*FleteLb*(1+IVA)+M31*(1+RecargoCIF)*IVA)) | R31: =IF(AND(ISNUMBER(P31),ISNUMBER(Q31)),IF(P31<=Q31,"Local","Amazon"),IF(ISNUMBER(P31),"Local",IF(ISNUMBER(Q31),"Amazon","—"))) | S31: Local | T31: =IF(S31="Amazon",IF(ISNUMBER(Q31),Q31,0),IF(ISNUMBER(P31),P31,0)) | U31: Por comprar | V31: =SUMIFS('Registro de gastos'!$F$10:$F$400,'Registro de gastos'!$B$10:$B$400,A31) | W31: =IF(OR(U31="Por comprar",U31="Cotizado"),MAX(T31-V31,0),0) | X31: =V31+W31 | Z31: https://www.amazon.com/dp/B00144862U | AB31: =IF(AND(S31="Amazon",ISNUMBER(M31),W31>0),ROUNDUP(G31/N31,0)*M31,0) | AC31: =IF(AND(ISNUMBER(P31),ISNUMBER(Q31)),MIN(P31,Q31),IF(ISNUMBER(P31),P31,IF(ISNUMBER(Q31),Q31,0)))
A32: CAB-05 | B32: Cabezal de disco | C32: Resorte de compresión | D32: Ø15–16 × 30 mm, alambre 0.5–0.6 (Ø int. ≥ 13.5, sólido ≤ 6 mm) | E32: Porta-plumón con amortiguación | F32: MathBot | G32: 1 | H32: Obligatorio | I32: Vidrí / Freund | J32: 0.5 | K32: 1 | L32: Estimado | M32: 6.58 | N32: 1 | O32: 0.5 | P32: =IF(J32="","",ROUNDUP(G32/K32,0)*J32*(1-IF(ISNUMBER(SEARCH("Casa Rivas",I32)),DescCasaRivas,0))) | Q32: =IF(M32="","",ROUNDUP(G32/N32,0)*(M32*(1+TasaVentasEEUU)+O32*FleteLb*(1+IVA)+M32*(1+RecargoCIF)*IVA)) | R32: =IF(AND(ISNUMBER(P32),ISNUMBER(Q32)),IF(P32<=Q32,"Local","Amazon"),IF(ISNUMBER(P32),"Local",IF(ISNUMBER(Q32),"Amazon","—"))) | S32: Local | T32: =IF(S32="Amazon",IF(ISNUMBER(Q32),Q32,0),IF(ISNUMBER(P32),P32,0)) | U32: Por comprar | V32: =SUMIFS('Registro de gastos'!$F$10:$F$400,'Registro de gastos'!$B$10:$B$400,A32) | W32: =IF(OR(U32="Por comprar",U32="Cotizado"),MAX(T32-V32,0),0) | X32: =V32+W32 | Z32: https://www.amazon.com/dp/B0F47T44GH | AA32: Va alrededor del plumón (Ø12): el de Ø10–12 × 20 no entra ni da 18 mm de levante. Ver Cabezal disco/README.md. | AB32: =IF(AND(S32="Amazon",ISNUMBER(M32),W32>0),ROUNDUP(G32/N32,0)*M32,0) | AC32: =IF(AND(ISNUMBER(P32),ISNUMBER(Q32)),MIN(P32,Q32),IF(ISNUMBER(P32),P32,IF(ISNUMBER(Q32),Q32,0)))
A33: CAB-06 | B33: Cabezal de disco | C33: Tornillería del cabezal A v3 | D33: 4 × M4×35 + tuerca + arandela + fijador de rosca; M3: 4×10, 1×12, 3×20, 1×35, 3×16 avellanados + 11 tuercas | E33: Placa + separador al J3 Coupler y montaje de las herramientas | F33: MathBot | G33: 1 | H33: Obligatorio | I33: Vidrí | J33: 0.6 | K33: 1 | L33: Estimado | P33: =IF(J33="","",ROUNDUP(G33/K33,0)*J33*(1-IF(ISNUMBER(SEARCH("Casa Rivas",I33)),DescCasaRivas,0))) | Q33: =IF(M33="","",ROUNDUP(G33/N33,0)*(M33*(1+TasaVentasEEUU)+O33*FleteLb*(1+IVA)+M33*(1+RecargoCIF)*IVA)) | R33: =IF(AND(ISNUMBER(P33),ISNUMBER(Q33)),IF(P33<=Q33,"Local","Amazon"),IF(ISNUMBER(P33),"Local",IF(ISNUMBER(Q33),"Amazon","—"))) | S33: Local | T33: =IF(S33="Amazon",IF(ISNUMBER(Q33),Q33,0),IF(ISNUMBER(P33),P33,0)) | U33: Por comprar | V33: =SUMIFS('Registro de gastos'!$F$10:$F$400,'Registro de gastos'!$B$10:$B$400,A33) | W33: =IF(OR(U33="Por comprar",U33="Cotizado"),MAX(T33-V33,0),0) | X33: =V33+W33 | AA33: El separador del electroimán ahora es impreso (hoja Impresión 3D). Lista por pieza en BRAZO SCARA/DISEÑO FINAL/Cabezal disco/README.md. | AB33: =IF(AND(S33="Amazon",ISNUMBER(M33),W33>0),ROUNDUP(G33/N33,0)*M33,0) | AC33: =IF(AND(ISNUMBER(P33),ISNUMBER(Q33)),MIN(P33,Q33),IF(ISNUMBER(P33),P33,IF(ISNUMBER(Q33),Q33,0)))
A34: MB-01 | B34: Electrónica MathBot | C34: MOSFET IRLZ44N + resistencias 220 Ω / 10 kΩ | D34: Nivel lógico | E34: Encender el electroimán desde D24 | F34: MathBot | G34: 1 | H34: Obligatorio | I34: Casa Rivas | J34: 1.5 | K34: 1 | L34: Estimado (hay en el país) | M34: 9.49 | N34: 1 | O34: 0.1 | P34: =IF(J34="","",ROUNDUP(G34/K34,0)*J34*(1-IF(ISNUMBER(SEARCH("Casa Rivas",I34)),DescCasaRivas,0))) | Q34: =IF(M34="","",ROUNDUP(G34/N34,0)*(M34*(1+TasaVentasEEUU)+O34*FleteLb*(1+IVA)+M34*(1+RecargoCIF)*IVA)) | R34: =IF(AND(ISNUMBER(P34),ISNUMBER(Q34)),IF(P34<=Q34,"Local","Amazon"),IF(ISNUMBER(P34),"Local",IF(ISNUMBER(Q34),"Amazon","—"))) | S34: Local | T34: =IF(S34="Amazon",IF(ISNUMBER(Q34),Q34,0),IF(ISNUMBER(P34),P34,0)) | U34: Por comprar | V34: =SUMIFS('Registro de gastos'!$F$10:$F$400,'Registro de gastos'!$B$10:$B$400,A34) | W34: =IF(OR(U34="Por comprar",U34="Cotizado"),MAX(T34-V34,0),0) | X34: =V34+W34 | Z34: https://www.amazon.com/dp/B088NH81S9 | AA34: Alternativa ya armada: módulo D4184 (Amazon). | AB34: =IF(AND(S34="Amazon",ISNUMBER(M34),W34>0),ROUNDUP(G34/N34,0)*M34,0) | AC34: =IF(AND(ISNUMBER(P34),ISNUMBER(Q34)),MIN(P34,Q34),IF(ISNUMBER(P34),P34,IF(ISNUMBER(Q34),Q34,0)))
A35: MB-02 | B35: Electrónica MathBot | C35: Diodo 1N5819 o 1N4007 | E35: Flyback del electroimán | F35: MathBot | G35: 2 | H35: Obligatorio | I35: Casa Rivas | J35: 0.15 | K35: 1 | L35: Estimado | M35: 7.99 | N35: 100 | O35: 0.1 | P35: =IF(J35="","",ROUNDUP(G35/K35,0)*J35*(1-IF(ISNUMBER(SEARCH("Casa Rivas",I35)),DescCasaRivas,0))) | Q35: =IF(M35="","",ROUNDUP(G35/N35,0)*(M35*(1+TasaVentasEEUU)+O35*FleteLb*(1+IVA)+M35*(1+RecargoCIF)*IVA)) | R35: =IF(AND(ISNUMBER(P35),ISNUMBER(Q35)),IF(P35<=Q35,"Local","Amazon"),IF(ISNUMBER(P35),"Local",IF(ISNUMBER(Q35),"Amazon","—"))) | S35: Local | T35: =IF(S35="Amazon",IF(ISNUMBER(Q35),Q35,0),IF(ISNUMBER(P35),P35,0)) | U35: Por comprar | V35: =SUMIFS('Registro de gastos'!$F$10:$F$400,'Registro de gastos'!$B$10:$B$400,A35) | W35: =IF(OR(U35="Por comprar",U35="Cotizado"),MAX(T35-V35,0),0) | X35: =V35+W35 | Z35: https://www.amazon.com/dp/B079KG1TN2 | AB35: =IF(AND(S35="Amazon",ISNUMBER(M35),W35>0),ROUNDUP(G35/N35,0)*M35,0) | AC35: =IF(AND(ISNUMBER(P35),ISNUMBER(Q35)),MIN(P35,Q35),IF(ISNUMBER(P35),P35,IF(ISNUMBER(Q35),Q35,0)))
A36: MB-03 | B36: Electrónica MathBot | C36: Optoacoplador PC817 + resistencias | E36: Llevar la señal de 12 V del sensor a D22 | F36: MathBot | G36: 1 | H36: Obligatorio | I36: Casa Rivas | J36: 0.6 | K36: 1 | L36: Estimado | M36: 6.99 | N36: 1 | O36: 0.1 | P36: =IF(J36="","",ROUNDUP(G36/K36,0)*J36*(1-IF(ISNUMBER(SEARCH("Casa Rivas",I36)),DescCasaRivas,0))) | Q36: =IF(M36="","",ROUNDUP(G36/N36,0)*(M36*(1+TasaVentasEEUU)+O36*FleteLb*(1+IVA)+M36*(1+RecargoCIF)*IVA)) | R36: =IF(AND(ISNUMBER(P36),ISNUMBER(Q36)),IF(P36<=Q36,"Local","Amazon"),IF(ISNUMBER(P36),"Local",IF(ISNUMBER(Q36),"Amazon","—"))) | S36: Local | T36: =IF(S36="Amazon",IF(ISNUMBER(Q36),Q36,0),IF(ISNUMBER(P36),P36,0)) | U36: Por comprar | V36: =SUMIFS('Registro de gastos'!$F$10:$F$400,'Registro de gastos'!$B$10:$B$400,A36) | W36: =IF(OR(U36="Por comprar",U36="Cotizado"),MAX(T36-V36,0),0) | X36: =V36+W36 | Z36: https://www.amazon.com/dp/B0B5383L69 | AA36: Amazon: módulo armado NOYITO. | AB36: =IF(AND(S36="Amazon",ISNUMBER(M36),W36>0),ROUNDUP(G36/N36,0)*M36,0) | AC36: =IF(AND(ISNUMBER(P36),ISNUMBER(Q36)),MIN(P36,Q36),IF(ISNUMBER(P36),P36,IF(ISNUMBER(Q36),Q36,0)))
A37: MB-04 | B37: Electrónica MathBot | C37: Convertidor buck LM2596 | D37: 12 → 6 V, 3 A | E37: Alimentar el servo del cabezal | F37: MathBot | G37: 1 | H37: Obligatorio | I37: Casa Rivas / ArduStore SV | J37: 4 | K37: 1 | L37: Estimado | M37: 7.99 | N37: 5 | O37: 0.2 | P37: =IF(J37="","",ROUNDUP(G37/K37,0)*J37*(1-IF(ISNUMBER(SEARCH("Casa Rivas",I37)),DescCasaRivas,0))) | Q37: =IF(M37="","",ROUNDUP(G37/N37,0)*(M37*(1+TasaVentasEEUU)+O37*FleteLb*(1+IVA)+M37*(1+RecargoCIF)*IVA)) | R37: =IF(AND(ISNUMBER(P37),ISNUMBER(Q37)),IF(P37<=Q37,"Local","Amazon"),IF(ISNUMBER(P37),"Local",IF(ISNUMBER(Q37),"Amazon","—"))) | S37: Local | T37: =IF(S37="Amazon",IF(ISNUMBER(Q37),Q37,0),IF(ISNUMBER(P37),P37,0)) | U37: Por comprar | V37: =SUMIFS('Registro de gastos'!$F$10:$F$400,'Registro de gastos'!$B$10:$B$400,A37) | W37: =IF(OR(U37="Por comprar",U37="Cotizado"),MAX(T37-V37,0),0) | X37: =V37+W37 | Z37: https://www.amazon.com/dp/B0DBVYP91F | AB37: =IF(AND(S37="Amazon",ISNUMBER(M37),W37>0),ROUNDUP(G37/N37,0)*M37,0) | AC37: =IF(AND(ISNUMBER(P37),ISNUMBER(Q37)),MIN(P37,Q37),IF(ISNUMBER(P37),P37,IF(ISNUMBER(Q37),Q37,0)))
A38: MB-05 | B38: Electrónica MathBot | C38: Placa perforada 5 × 7 cm + borneras + headers | E38: Montar la interfaz sobre la base | F38: MathBot | G38: 1 | H38: Obligatorio | I38: Casa Rivas | J38: 2.5 | K38: 1 | L38: Estimado | P38: =IF(J38="","",ROUNDUP(G38/K38,0)*J38*(1-IF(ISNUMBER(SEARCH("Casa Rivas",I38)),DescCasaRivas,0))) | Q38: =IF(M38="","",ROUNDUP(G38/N38,0)*(M38*(1+TasaVentasEEUU)+O38*FleteLb*(1+IVA)+M38*(1+RecargoCIF)*IVA)) | R38: =IF(AND(ISNUMBER(P38),ISNUMBER(Q38)),IF(P38<=Q38,"Local","Amazon"),IF(ISNUMBER(P38),"Local",IF(ISNUMBER(Q38),"Amazon","—"))) | S38: Local | T38: =IF(S38="Amazon",IF(ISNUMBER(Q38),Q38,0),IF(ISNUMBER(P38),P38,0)) | U38: Por comprar | V38: =SUMIFS('Registro de gastos'!$F$10:$F$400,'Registro de gastos'!$B$10:$B$400,A38) | W38: =IF(OR(U38="Por comprar",U38="Cotizado"),MAX(T38-V38,0),0) | X38: =V38+W38 | AB38: =IF(AND(S38="Amazon",ISNUMBER(M38),W38>0),ROUNDUP(G38/N38,0)*M38,0) | AC38: =IF(AND(ISNUMBER(P38),ISNUMBER(Q38)),MIN(P38,Q38),IF(ISNUMBER(P38),P38,IF(ISNUMBER(Q38),Q38,0)))
A39: MB-06 | B39: Electrónica MathBot | C39: Cable multiconductor 6–8 hilos, AWG 24 | D39: Flexible, por metro | E39: Del cabezal a la base por los ejes huecos de J2 y J3 | F39: MathBot | G39: 2 | H39: Obligatorio | I39: Vidrí / Casa Rivas (cable de alarma) | J39: 0.8 | K39: 1 | L39: Estimado | P39: =IF(J39="","",ROUNDUP(G39/K39,0)*J39*(1-IF(ISNUMBER(SEARCH("Casa Rivas",I39)),DescCasaRivas,0))) | Q39: =IF(M39="","",ROUNDUP(G39/N39,0)*(M39*(1+TasaVentasEEUU)+O39*FleteLb*(1+IVA)+M39*(1+RecargoCIF)*IVA)) | R39: =IF(AND(ISNUMBER(P39),ISNUMBER(Q39)),IF(P39<=Q39,"Local","Amazon"),IF(ISNUMBER(P39),"Local",IF(ISNUMBER(Q39),"Amazon","—"))) | S39: Local | T39: =IF(S39="Amazon",IF(ISNUMBER(Q39),Q39,0),IF(ISNUMBER(P39),P39,0)) | U39: Por comprar | V39: =SUMIFS('Registro de gastos'!$F$10:$F$400,'Registro de gastos'!$B$10:$B$400,A39) | W39: =IF(OR(U39="Por comprar",U39="Cotizado"),MAX(T39-V39,0),0) | X39: =V39+W39 | AB39: =IF(AND(S39="Amazon",ISNUMBER(M39),W39>0),ROUNDUP(G39/N39,0)*M39,0) | AC39: =IF(AND(ISNUMBER(P39),ISNUMBER(Q39)),MIN(P39,Q39),IF(ISNUMBER(P39),P39,IF(ISNUMBER(Q39),Q39,0)))
A40: MB-07 | B40: Electrónica MathBot | C40: Pulsador NA (START) + hongo de paro NC | E40: Iniciar la misión (D26) y PARO (D28) | F40: MathBot | G40: 1 | H40: Obligatorio | I40: Casa Rivas / Steren | L40: Cotizar | P40: =IF(J40="","",ROUNDUP(G40/K40,0)*J40*(1-IF(ISNUMBER(SEARCH("Casa Rivas",I40)),DescCasaRivas,0))) | Q40: =IF(M40="","",ROUNDUP(G40/N40,0)*(M40*(1+TasaVentasEEUU)+O40*FleteLb*(1+IVA)+M40*(1+RecargoCIF)*IVA)) | R40: =IF(AND(ISNUMBER(P40),ISNUMBER(Q40)),IF(P40<=Q40,"Local","Amazon"),IF(ISNUMBER(P40),"Local",IF(ISNUMBER(Q40),"Amazon","—"))) | S40: Local | T40: =IF(S40="Amazon",IF(ISNUMBER(Q40),Q40,0),IF(ISNUMBER(P40),P40,0)) | U40: Por comprar | V40: =SUMIFS('Registro de gastos'!$F$10:$F$400,'Registro de gastos'!$B$10:$B$400,A40) | W40: =IF(OR(U40="Por comprar",U40="Cotizado"),MAX(T40-V40,0),0) | X40: =V40+W40 | AA40: El PARO solo es software (ver firmware/README.md). | AB40: =IF(AND(S40="Amazon",ISNUMBER(M40),W40>0),ROUNDUP(G40/N40,0)*M40,0) | AC40: =IF(AND(ISNUMBER(P40),ISNUMBER(Q40)),MIN(P40,Q40),IF(ISNUMBER(P40),P40,IF(ISNUMBER(Q40),Q40,0)))
A41: MB-08 | B41: Electrónica MathBot | C41: 3 LED (verde, amarillo, rojo) + buzzer + resistencias | D41: 220 Ω para los LED; 10 kΩ / 3.3 kΩ para el divisor de 12 V | E41: Estado (D30–D34), aviso (D36) y monitor de 12 V (A8) | F41: MathBot | G41: 1 | H41: Recomendado | I41: Casa Rivas | L41: Cotizar | P41: =IF(J41="","",ROUNDUP(G41/K41,0)*J41*(1-IF(ISNUMBER(SEARCH("Casa Rivas",I41)),DescCasaRivas,0))) | Q41: =IF(M41="","",ROUNDUP(G41/N41,0)*(M41*(1+TasaVentasEEUU)+O41*FleteLb*(1+IVA)+M41*(1+RecargoCIF)*IVA)) | R41: =IF(AND(ISNUMBER(P41),ISNUMBER(Q41)),IF(P41<=Q41,"Local","Amazon"),IF(ISNUMBER(P41),"Local",IF(ISNUMBER(Q41),"Amazon","—"))) | S41: Local | T41: =IF(S41="Amazon",IF(ISNUMBER(Q41),Q41,0),IF(ISNUMBER(P41),P41,0)) | U41: Por comprar | V41: =SUMIFS('Registro de gastos'!$F$10:$F$400,'Registro de gastos'!$B$10:$B$400,A41) | W41: =IF(OR(U41="Por comprar",U41="Cotizado"),MAX(T41-V41,0),0) | X41: =V41+W41 | AB41: =IF(AND(S41="Amazon",ISNUMBER(M41),W41>0),ROUNDUP(G41/N41,0)*M41,0) | AC41: =IF(AND(ISNUMBER(P41),ISNUMBER(Q41)),MIN(P41,Q41),IF(ISNUMBER(P41),P41,IF(ISNUMBER(Q41),Q41,0)))
A42: TOR-01 | B42: Tornillería | C42: Surtido de tornillos Allen M3/M4/M5 + tuercas | D42: ≈ 20 M3 × 8–16, 45–55 M4 × 16–30 y sus tuercas | E42: Tornillos chicos del brazo: motores, abrazaderas de varilla, tapas, placas Z y acoples | F42: HTM | G42: 1 | H42: Obligatorio | I42: Vidrí / Freund (por pieza) | J42: 15 | K42: 1 | L42: Estimado | M42: 22.99 | N42: 1 | O42: 2.5 | P42: =IF(J42="","",ROUNDUP(G42/K42,0)*J42*(1-IF(ISNUMBER(SEARCH("Casa Rivas",I42)),DescCasaRivas,0))) | Q42: =IF(M42="","",ROUNDUP(G42/N42,0)*(M42*(1+TasaVentasEEUU)+O42*FleteLb*(1+IVA)+M42*(1+RecargoCIF)*IVA)) | R42: =IF(AND(ISNUMBER(P42),ISNUMBER(Q42)),IF(P42<=Q42,"Local","Amazon"),IF(ISNUMBER(P42),"Local",IF(ISNUMBER(Q42),"Amazon","—"))) | S42: Local | T42: =IF(S42="Amazon",IF(ISNUMBER(Q42),Q42,0),IF(ISNUMBER(P42),P42,0)) | U42: Por comprar | V42: =SUMIFS('Registro de gastos'!$F$10:$F$400,'Registro de gastos'!$B$10:$B$400,A42) | W42: =IF(OR(U42="Por comprar",U42="Cotizado"),MAX(T42-V42,0),0) | X42: =V42+W42 | Z42: https://www.amazon.com/dp/B0FG2964F5 | AA42: El artículo trae la lista en una imagen y el CAD no los modela; cantidades estimadas por los agujeros del CAD (Ø3.2 = M3, Ø4.1 = M4): 16 M3 × 8–12 (4 por NEMA), 4 M3 × 16 (tuerca del husillo T8), 16 M4 × 20 (8 abrazaderas de varilla), 6 M4 × 20 (J2 Coupler → brazo 2) y 20–30 M4 × 16–30 (tapas, placas Z, polea de J3). El surtido de Amazon cubre todo pero pesa 2.5 lb. | AB42: =IF(AND(S42="Amazon",ISNUMBER(M42),W42>0),ROUNDUP(G42/N42,0)*M42,0) | AC42: =IF(AND(ISNUMBER(P42),ISNUMBER(Q42)),MIN(P42,Q42),IF(ISNUMBER(P42),P42,IF(ISNUMBER(Q42),Q42,0)))
A43: TOR-02 | B43: Tornillería | C43: Perno M4 × 60 + tuerca de seguridad | D43: DIN 912, tuerca con nylon | E43: Unir la polea de 110 dientes con el acople J1 | F43: HTM | G43: 4 | H43: Obligatorio | I43: Vidrí | J43: 0.3 | K43: 1 | L43: Estimado | P43: =IF(J43="","",ROUNDUP(G43/K43,0)*J43*(1-IF(ISNUMBER(SEARCH("Casa Rivas",I43)),DescCasaRivas,0))) | Q43: =IF(M43="","",ROUNDUP(G43/N43,0)*(M43*(1+TasaVentasEEUU)+O43*FleteLb*(1+IVA)+M43*(1+RecargoCIF)*IVA)) | R43: =IF(AND(ISNUMBER(P43),ISNUMBER(Q43)),IF(P43<=Q43,"Local","Amazon"),IF(ISNUMBER(P43),"Local",IF(ISNUMBER(Q43),"Amazon","—"))) | S43: Local | T43: =IF(S43="Amazon",IF(ISNUMBER(Q43),Q43,0),IF(ISNUMBER(P43),P43,0)) | U43: Por comprar | V43: =SUMIFS('Registro de gastos'!$F$10:$F$400,'Registro de gastos'!$B$10:$B$400,A43) | W43: =IF(OR(U43="Por comprar",U43="Cotizado"),MAX(T43-V43,0),0) | X43: =V43+W43 | AA43: Medida del CAD (M4 60mm - Bolts en J1). El texto del artículo decía M4 × 55. | AB43: =IF(AND(S43="Amazon",ISNUMBER(M43),W43>0),ROUNDUP(G43/N43,0)*M43,0) | AC43: =IF(AND(ISNUMBER(P43),ISNUMBER(Q43)),MIN(P43,Q43),IF(ISNUMBER(P43),P43,IF(ISNUMBER(Q43),Q43,0)))
A44: TOR-03 | B44: Tornillería | C44: Perno M4 × 50 + tuerca de seguridad | D44: DIN 912, tuerca con nylon | E44: Unir la polea de 92 dientes con el acople J2 | F44: HTM | G44: 4 | H44: Obligatorio | I44: Vidrí | J44: 0.3 | K44: 1 | L44: Estimado | P44: =IF(J44="","",ROUNDUP(G44/K44,0)*J44*(1-IF(ISNUMBER(SEARCH("Casa Rivas",I44)),DescCasaRivas,0))) | Q44: =IF(M44="","",ROUNDUP(G44/N44,0)*(M44*(1+TasaVentasEEUU)+O44*FleteLb*(1+IVA)+M44*(1+RecargoCIF)*IVA)) | R44: =IF(AND(ISNUMBER(P44),ISNUMBER(Q44)),IF(P44<=Q44,"Local","Amazon"),IF(ISNUMBER(P44),"Local",IF(ISNUMBER(Q44),"Amazon","—"))) | S44: Local | T44: =IF(S44="Amazon",IF(ISNUMBER(Q44),Q44,0),IF(ISNUMBER(P44),P44,0)) | U44: Por comprar | V44: =SUMIFS('Registro de gastos'!$F$10:$F$400,'Registro de gastos'!$B$10:$B$400,A44) | W44: =IF(OR(U44="Por comprar",U44="Cotizado"),MAX(T44-V44,0),0) | X44: =V44+W44 | AA44: Medida del CAD (M4 50mm - Bolts en J2). | AB44: =IF(AND(S44="Amazon",ISNUMBER(M44),W44>0),ROUNDUP(G44/N44,0)*M44,0) | AC44: =IF(AND(ISNUMBER(P44),ISNUMBER(Q44)),MIN(P44,Q44),IF(ISNUMBER(P44),P44,IF(ISNUMBER(Q44),Q44,0)))
A45: TOR-04 | B45: Tornillería | C45: Perno M8 × 45 + arandela + tuerca de seguridad | E45: Eje de las poleas intermedias de J1 y J2 (1 c/u) | F45: HTM | G45: 2 | H45: Obligatorio | I45: Vidrí | J45: 0.75 | K45: 1 | L45: Estimado | P45: =IF(J45="","",ROUNDUP(G45/K45,0)*J45*(1-IF(ISNUMBER(SEARCH("Casa Rivas",I45)),DescCasaRivas,0))) | Q45: =IF(M45="","",ROUNDUP(G45/N45,0)*(M45*(1+TasaVentasEEUU)+O45*FleteLb*(1+IVA)+M45*(1+RecargoCIF)*IVA)) | R45: =IF(AND(ISNUMBER(P45),ISNUMBER(Q45)),IF(P45<=Q45,"Local","Amazon"),IF(ISNUMBER(P45),"Local",IF(ISNUMBER(Q45),"Amazon","—"))) | S45: Local | T45: =IF(S45="Amazon",IF(ISNUMBER(Q45),Q45,0),IF(ISNUMBER(P45),P45,0)) | U45: Por comprar | V45: =SUMIFS('Registro de gastos'!$F$10:$F$400,'Registro de gastos'!$B$10:$B$400,A45) | W45: =IF(OR(U45="Por comprar",U45="Cotizado"),MAX(T45-V45,0),0) | X45: =V45+W45 | AB45: =IF(AND(S45="Amazon",ISNUMBER(M45),W45>0),ROUNDUP(G45/N45,0)*M45,0) | AC45: =IF(AND(ISNUMBER(P45),ISNUMBER(Q45)),MIN(P45,Q45),IF(ISNUMBER(P45),P45,IF(ISNUMBER(Q45),Q45,0)))
A46: TOR-05 | B46: Tornillería | C46: Perno M5 × 35 + tuercas | D46: 2 tuercas por perno | E46: Tensores de correa | F46: HTM | G46: 4 | H46: Recomendado | I46: Vidrí | J46: 0.25 | K46: 1 | L46: Estimado | P46: =IF(J46="","",ROUNDUP(G46/K46,0)*J46*(1-IF(ISNUMBER(SEARCH("Casa Rivas",I46)),DescCasaRivas,0))) | Q46: =IF(M46="","",ROUNDUP(G46/N46,0)*(M46*(1+TasaVentasEEUU)+O46*FleteLb*(1+IVA)+M46*(1+RecargoCIF)*IVA)) | R46: =IF(AND(ISNUMBER(P46),ISNUMBER(Q46)),IF(P46<=Q46,"Local","Amazon"),IF(ISNUMBER(P46),"Local",IF(ISNUMBER(Q46),"Amazon","—"))) | S46: Local | T46: =IF(S46="Amazon",IF(ISNUMBER(Q46),Q46,0),IF(ISNUMBER(P46),P46,0)) | U46: Por comprar | V46: =SUMIFS('Registro de gastos'!$F$10:$F$400,'Registro de gastos'!$B$10:$B$400,A46) | W46: =IF(OR(U46="Por comprar",U46="Cotizado"),MAX(T46-V46,0),0) | X46: =V46+W46 | AB46: =IF(AND(S46="Amazon",ISNUMBER(M46),W46>0),ROUNDUP(G46/N46,0)*M46,0) | AC46: =IF(AND(ISNUMBER(P46),ISNUMBER(Q46)),MIN(P46,Q46),IF(ISNUMBER(P46),P46,IF(ISNUMBER(Q46),Q46,0)))
A47: TOR-06 | B47: Tornillería | C47: Tornillo M4 + tuerca | D47: ≈ M4 × 40: grosor de la base + 20 mm de madera | E47: Fijar la base a la madera (12 agujeros) | F47: HTM | G47: 12 | H47: Recomendado | I47: Vidrí | J47: 0.12 | K47: 1 | L47: Estimado | P47: =IF(J47="","",ROUNDUP(G47/K47,0)*J47*(1-IF(ISNUMBER(SEARCH("Casa Rivas",I47)),DescCasaRivas,0))) | Q47: =IF(M47="","",ROUNDUP(G47/N47,0)*(M47*(1+TasaVentasEEUU)+O47*FleteLb*(1+IVA)+M47*(1+RecargoCIF)*IVA)) | R47: =IF(AND(ISNUMBER(P47),ISNUMBER(Q47)),IF(P47<=Q47,"Local","Amazon"),IF(ISNUMBER(P47),"Local",IF(ISNUMBER(Q47),"Amazon","—"))) | S47: Local | T47: =IF(S47="Amazon",IF(ISNUMBER(Q47),Q47,0),IF(ISNUMBER(P47),P47,0)) | U47: Por comprar | V47: =SUMIFS('Registro de gastos'!$F$10:$F$400,'Registro de gastos'!$B$10:$B$400,A47) | W47: =IF(OR(U47="Por comprar",U47="Cotizado"),MAX(T47-V47,0),0) | X47: =V47+W47 | AA47: Midan la base antes de comprar el largo. | AB47: =IF(AND(S47="Amazon",ISNUMBER(M47),W47>0),ROUNDUP(G47/N47,0)*M47,0) | AC47: =IF(AND(ISNUMBER(P47),ISNUMBER(Q47)),MIN(P47,Q47),IF(ISNUMBER(P47),P47,IF(ISNUMBER(Q47),Q47,0)))
A48: TOR-07 | B48: Tornillería | C48: Tornillo M2 × 10 + tuerca | D48: O autorroscante para plástico | E48: Finales de carrera (2 por switch) | F48: HTM | G48: 8 | H48: Obligatorio | I48: Vidrí / Casa Rivas | J48: 0.1 | K48: 1 | L48: Estimado | P48: =IF(J48="","",ROUNDUP(G48/K48,0)*J48*(1-IF(ISNUMBER(SEARCH("Casa Rivas",I48)),DescCasaRivas,0))) | Q48: =IF(M48="","",ROUNDUP(G48/N48,0)*(M48*(1+TasaVentasEEUU)+O48*FleteLb*(1+IVA)+M48*(1+RecargoCIF)*IVA)) | R48: =IF(AND(ISNUMBER(P48),ISNUMBER(Q48)),IF(P48<=Q48,"Local","Amazon"),IF(ISNUMBER(P48),"Local",IF(ISNUMBER(Q48),"Amazon","—"))) | S48: Local | T48: =IF(S48="Amazon",IF(ISNUMBER(Q48),Q48,0),IF(ISNUMBER(P48),P48,0)) | U48: Por comprar | V48: =SUMIFS('Registro de gastos'!$F$10:$F$400,'Registro de gastos'!$B$10:$B$400,A48) | W48: =IF(OR(U48="Por comprar",U48="Cotizado"),MAX(T48-V48,0),0) | X48: =V48+W48 | AA48: Si los finales de carrera traen tornillos, no hace falta. | AB48: =IF(AND(S48="Amazon",ISNUMBER(M48),W48>0),ROUNDUP(G48/N48,0)*M48,0) | AC48: =IF(AND(ISNUMBER(P48),ISNUMBER(Q48)),MIN(P48,Q48),IF(ISNUMBER(P48),P48,IF(ISNUMBER(Q48),Q48,0)))
A49: TOR-08 | B49: Tornillería | C49: Perno M5 × 25 | D49: DIN 912 | E49: Plataforma Z → brazo 1 | F49: HTM | G49: 4 | H49: Obligatorio | I49: Vidrí | J49: 0.2 | K49: 1 | L49: Estimado | P49: =IF(J49="","",ROUNDUP(G49/K49,0)*J49*(1-IF(ISNUMBER(SEARCH("Casa Rivas",I49)),DescCasaRivas,0))) | Q49: =IF(M49="","",ROUNDUP(G49/N49,0)*(M49*(1+TasaVentasEEUU)+O49*FleteLb*(1+IVA)+M49*(1+RecargoCIF)*IVA)) | R49: =IF(AND(ISNUMBER(P49),ISNUMBER(Q49)),IF(P49<=Q49,"Local","Amazon"),IF(ISNUMBER(P49),"Local",IF(ISNUMBER(Q49),"Amazon","—"))) | S49: Local | T49: =IF(S49="Amazon",IF(ISNUMBER(Q49),Q49,0),IF(ISNUMBER(P49),P49,0)) | U49: Por comprar | V49: =SUMIFS('Registro de gastos'!$F$10:$F$400,'Registro de gastos'!$B$10:$B$400,A49) | W49: =IF(OR(U49="Por comprar",U49="Cotizado"),MAX(T49-V49,0),0) | X49: =V49+W49 | AA49: Medida del simulador (Z-axis Mount Platform). | AB49: =IF(AND(S49="Amazon",ISNUMBER(M49),W49>0),ROUNDUP(G49/N49,0)*M49,0) | AC49: =IF(AND(ISNUMBER(P49),ISNUMBER(Q49)),MIN(P49,Q49),IF(ISNUMBER(P49),P49,IF(ISNUMBER(Q49),Q49,0)))
A50: VAR-01 | B50: Impresión y varios | C50: Filamento PLA+ 1.75 mm | D50: Rollo de 1 kg | E50: Todas las piezas impresas (ver hoja Impresión 3D) | F50: HTM | G50: ='Impresión 3D'!$B$6 | H50: Obligatorio | I50: El Changarro (PLA 1 kg) | J50: 27.99 | K50: 1 | L50: Indexado en buscador (oferta) | M50: 11.19 | N50: 1 | O50: 2.9 | P50: =IF(J50="","",ROUNDUP(G50/K50,0)*J50*(1-IF(ISNUMBER(SEARCH("Casa Rivas",I50)),DescCasaRivas,0))) | Q50: =IF(M50="","",ROUNDUP(G50/N50,0)*(M50*(1+TasaVentasEEUU)+O50*FleteLb*(1+IVA)+M50*(1+RecargoCIF)*IVA)) | R50: =IF(AND(ISNUMBER(P50),ISNUMBER(Q50)),IF(P50<=Q50,"Local","Amazon"),IF(ISNUMBER(P50),"Local",IF(ISNUMBER(Q50),"Amazon","—"))) | S50: Amazon | T50: =IF(S50="Amazon",IF(ISNUMBER(Q50),Q50,0),IF(ISNUMBER(P50),P50,0)) | U50: Ya lo tenemos | V50: =SUMIFS('Registro de gastos'!$F$10:$F$400,'Registro de gastos'!$B$10:$B$400,A50) | W50: =IF(OR(U50="Por comprar",U50="Cotizado"),MAX(T50-V50,0),0) | X50: =V50+W50 | Z50: https://www.amazon.com/dp/B07XG3RM58 | AA50: Impresión gratuita: todas las piezas impresas quedan sin costo. Avalon Tech publicaba USD 30, pero cerró su tienda en línea en jul-2026: preguntar por WhatsApp. Si la universidad imprime, poner 'Ya lo tenemos'. | AB50: =IF(AND(S50="Amazon",ISNUMBER(M50),W50>0),ROUNDUP(G50/N50,0)*M50,0) | AC50: =IF(AND(ISNUMBER(P50),ISNUMBER(Q50)),MIN(P50,Q50),IF(ISNUMBER(P50),P50,IF(ISNUMBER(Q50),Q50,0)))
A51: VAR-02 | B51: Impresión y varios | C51: Cinchos sujetacables | D51: Paquete corto, negro | E51: Ordenar los cables | F51: HTM | G51: 1 | H51: Recomendado | I51: Steren (TY24NE) | J51: 2.49 | K51: 1 | L51: Verificado en línea 06-oct-2026 | P51: =IF(J51="","",ROUNDUP(G51/K51,0)*J51*(1-IF(ISNUMBER(SEARCH("Casa Rivas",I51)),DescCasaRivas,0))) | Q51: =IF(M51="","",ROUNDUP(G51/N51,0)*(M51*(1+TasaVentasEEUU)+O51*FleteLb*(1+IVA)+M51*(1+RecargoCIF)*IVA)) | R51: =IF(AND(ISNUMBER(P51),ISNUMBER(Q51)),IF(P51<=Q51,"Local","Amazon"),IF(ISNUMBER(P51),"Local",IF(ISNUMBER(Q51),"Amazon","—"))) | S51: Local | T51: =IF(S51="Amazon",IF(ISNUMBER(Q51),Q51,0),IF(ISNUMBER(P51),P51,0)) | U51: Por comprar | V51: =SUMIFS('Registro de gastos'!$F$10:$F$400,'Registro de gastos'!$B$10:$B$400,A51) | W51: =IF(OR(U51="Por comprar",U51="Cotizado"),MAX(T51-V51,0),0) | X51: =V51+W51 | AB51: =IF(AND(S51="Amazon",ISNUMBER(M51),W51>0),ROUNDUP(G51/N51,0)*M51,0) | AC51: =IF(AND(ISNUMBER(P51),ISNUMBER(Q51)),MIN(P51,Q51),IF(ISNUMBER(P51),P51,IF(ISNUMBER(Q51),Q51,0)))
A52: VAR-03 | B52: Impresión y varios | C52: Funda trenzada para cables 1/4" | E52: Mazo de cables de la columna | F52: HTM | G52: 1 | H52: Opcional | M52: 9.99 | N52: 1 | O52: 0.3 | P52: =IF(J52="","",ROUNDUP(G52/K52,0)*J52*(1-IF(ISNUMBER(SEARCH("Casa Rivas",I52)),DescCasaRivas,0))) | Q52: =IF(M52="","",ROUNDUP(G52/N52,0)*(M52*(1+TasaVentasEEUU)+O52*FleteLb*(1+IVA)+M52*(1+RecargoCIF)*IVA)) | R52: =IF(AND(ISNUMBER(P52),ISNUMBER(Q52)),IF(P52<=Q52,"Local","Amazon"),IF(ISNUMBER(P52),"Local",IF(ISNUMBER(Q52),"Amazon","—"))) | S52: Amazon | T52: =IF(S52="Amazon",IF(ISNUMBER(Q52),Q52,0),IF(ISNUMBER(P52),P52,0)) | U52: No comprar | V52: =SUMIFS('Registro de gastos'!$F$10:$F$400,'Registro de gastos'!$B$10:$B$400,A52) | W52: =IF(OR(U52="Por comprar",U52="Cotizado"),MAX(T52-V52,0),0) | X52: =V52+W52 | Z52: https://www.amazon.com/dp/B07RZXSJBM | AB52: =IF(AND(S52="Amazon",ISNUMBER(M52),W52>0),ROUNDUP(G52/N52,0)*M52,0) | AC52: =IF(AND(ISNUMBER(P52),ISNUMBER(Q52)),MIN(P52,Q52),IF(ISNUMBER(P52),P52,IF(ISNUMBER(Q52),Q52,0)))
A53: VAR-04 | B53: Impresión y varios | C53: Tubo termorretráctil (surtido) | E53: Aislar empalmes | F53: MathBot | G53: 1 | H53: Recomendado | I53: Casa Rivas | J53: 2 | K53: 1 | L53: Estimado | M53: 6.64 | N53: 1 | O53: 0.3 | P53: =IF(J53="","",ROUNDUP(G53/K53,0)*J53*(1-IF(ISNUMBER(SEARCH("Casa Rivas",I53)),DescCasaRivas,0))) | Q53: =IF(M53="","",ROUNDUP(G53/N53,0)*(M53*(1+TasaVentasEEUU)+O53*FleteLb*(1+IVA)+M53*(1+RecargoCIF)*IVA)) | R53: =IF(AND(ISNUMBER(P53),ISNUMBER(Q53)),IF(P53<=Q53,"Local","Amazon"),IF(ISNUMBER(P53),"Local",IF(ISNUMBER(Q53),"Amazon","—"))) | S53: Local | T53: =IF(S53="Amazon",IF(ISNUMBER(Q53),Q53,0),IF(ISNUMBER(P53),P53,0)) | U53: Por comprar | V53: =SUMIFS('Registro de gastos'!$F$10:$F$400,'Registro de gastos'!$B$10:$B$400,A53) | W53: =IF(OR(U53="Por comprar",U53="Cotizado"),MAX(T53-V53,0),0) | X53: =V53+W53 | Z53: https://www.amazon.com/dp/B01MFA3OFA | AB53: =IF(AND(S53="Amazon",ISNUMBER(M53),W53>0),ROUNDUP(G53/N53,0)*M53,0) | AC53: =IF(AND(ISNUMBER(P53),ISNUMBER(Q53)),MIN(P53,Q53),IF(ISNUMBER(P53),P53,IF(ISNUMBER(Q53),Q53,0)))
A54: VAR-05 | B54: Impresión y varios | C54: Gestión de casillero (por envío) | E54: Cargo fijo por paquete consolidado | F54: MathBot | G54: =EnviosCasillero | H54: Obligatorio | I54: Casillero en Miami (p. ej. QuickBox) | J54: =GestionEnvio | K54: 1 | L54: Estimado | P54: =IF(J54="","",ROUNDUP(G54/K54,0)*J54*(1-IF(ISNUMBER(SEARCH("Casa Rivas",I54)),DescCasaRivas,0))) | Q54: =IF(M54="","",ROUNDUP(G54/N54,0)*(M54*(1+TasaVentasEEUU)+O54*FleteLb*(1+IVA)+M54*(1+RecargoCIF)*IVA)) | R54: =IF(AND(ISNUMBER(P54),ISNUMBER(Q54)),IF(P54<=Q54,"Local","Amazon"),IF(ISNUMBER(P54),"Local",IF(ISNUMBER(Q54),"Amazon","—"))) | S54: Local | T54: =IF(S54="Amazon",IF(ISNUMBER(Q54),Q54,0),IF(ISNUMBER(P54),P54,0)) | U54: Por comprar | V54: =SUMIFS('Registro de gastos'!$F$10:$F$400,'Registro de gastos'!$B$10:$B$400,A54) | W54: =IF(OR(U54="Por comprar",U54="Cotizado"),MAX(T54-V54,0),0) | X54: =V54+W54 | AA54: El flete por libra ya va dentro del 'Total Amazon puesto en SV'. Esta línea es solo la gestión; ajusten el número de envíos en Supuestos. | AB54: =IF(AND(S54="Amazon",ISNUMBER(M54),W54>0),ROUNDUP(G54/N54,0)*M54,0) | AC54: =IF(AND(ISNUMBER(P54),ISNUMBER(Q54)),MIN(P54,Q54),IF(ISNUMBER(P54),P54,IF(ISNUMBER(Q54),Q54,0)))
C55: Totales | P55: =SUM(P5:P54) | Q55: =SUM(Q5:Q54) | T55: =SUM(T5:T54) | V55: =SUM(V5:V54) | W55: =SUM(W5:W54) | X55: =SUM(X5:X54) | AB55: =SUM(AB5:AB54) | AC55: =SUM(AC5:AC54)
C56: Nota: 'Total local' y 'Total Amazon' suman todas las filas aunque no se compren; el costo real del proyecto está en 'Proyección'.
C57: Naranja en 'Fuente elegida' = hay una opción más barata. Gris = fila que no se compra (no suma).

Sheet Registro de gastos
A1: Registro de gastos
A2: Una fila por pago. El ID enlaza con la lista de materiales: el 'Gastado real' de cada ítem y del resumen se calcula de aquí. Al terminar una compra, cambien el Estado del ítem a 'Comprado'.
A4: Ejemplo de cómo llenar una fila (no se suma):
A5: Fecha | B5: ID ítem | C5: Componente | D5: Tienda | E5: Cantidad | F5: Monto pagado (USD) | G5: Pagó | H5: Método de pago | I5: Comprobante | J5: Notas
A6: 06/10/2026 | B6: ELE-01 | C6: Motor paso a paso NEMA 17, 40 mm | D6: Electrónica 2001 | E6: 3 | F6: 36 | G6: Integrante 1 | H6: Tarjeta | I6: Factura 1234 | J6: Pedido para retirar
A8: Pagos del proyecto
A9: Fecha | B9: ID ítem | C9: Componente | D9: Tienda | E9: Cantidad | F9: Monto pagado (USD) | G9: Pagó | H9: Método de pago | I9: Comprobante | J9: Notas | L9: Total pagado
C10: =IF(B10="","",IFERROR(INDEX('Lista de materiales'!$C$5:$C$54,MATCH(B10,'Lista de materiales'!$A$5:$A$54,0)),"ID no existe")) | L10: =SUM(F10:F400)
C11: =IF(B11="","",IFERROR(INDEX('Lista de materiales'!$C$5:$C$54,MATCH(B11,'Lista de materiales'!$A$5:$A$54,0)),"ID no existe"))
C12: =IF(B12="","",IFERROR(INDEX('Lista de materiales'!$C$5:$C$54,MATCH(B12,'Lista de materiales'!$A$5:$A$54,0)),"ID no existe"))
C13: =IF(B13="","",IFERROR(INDEX('Lista de materiales'!$C$5:$C$54,MATCH(B13,'Lista de materiales'!$A$5:$A$54,0)),"ID no existe"))
C14: =IF(B14="","",IFERROR(INDEX('Lista de materiales'!$C$5:$C$54,MATCH(B14,'Lista de materiales'!$A$5:$A$54,0)),"ID no existe"))
C15: =IF(B15="","",IFERROR(INDEX('Lista de materiales'!$C$5:$C$54,MATCH(B15,'Lista de materiales'!$A$5:$A$54,0)),"ID no existe"))
C16: =IF(B16="","",IFERROR(INDEX('Lista de materiales'!$C$5:$C$54,MATCH(B16,'Lista de materiales'!$A$5:$A$54,0)),"ID no existe"))
C17: =IF(B17="","",IFERROR(INDEX('Lista de materiales'!$C$5:$C$54,MATCH(B17,'Lista de materiales'!$A$5:$A$54,0)),"ID no existe"))
C18: =IF(B18="","",IFERROR(INDEX('Lista de materiales'!$C$5:$C$54,MATCH(B18,'Lista de materiales'!$A$5:$A$54,0)),"ID no existe"))
C19: =IF(B19="","",IFERROR(INDEX('Lista de materiales'!$C$5:$C$54,MATCH(B19,'Lista de materiales'!$A$5:$A$54,0)),"ID no existe"))
C20: =IF(B20="","",IFERROR(INDEX('Lista de materiales'!$C$5:$C$54,MATCH(B20,'Lista de materiales'!$A$5:$A$54,0)),"ID no existe"))
C21: =IF(B21="","",IFERROR(INDEX('Lista de materiales'!$C$5:$C$54,MATCH(B21,'Lista de materiales'!$A$5:$A$54,0)),"ID no existe"))
C22: =IF(B22="","",IFERROR(INDEX('Lista de materiales'!$C$5:$C$54,MATCH(B22,'Lista de materiales'!$A$5:$A$54,0)),"ID no existe"))
... C400: =IF(B400="","",IFERROR(INDEX('Lista de materiales'!$C$5:$C$54,MATCH(B400,'Lista de materiales'!$A$5:$A$54,0)),"ID no existe"))

Sheet Impresión 3D
A1: Impresión 3D
A2: Gramos estimados con el volumen real de cada STL: paredes y techos de 1.1 mm sólidos + 25 % de relleno, PLA 1.24 g/cm³. Las poleas GT2 se imprimen (el artículo usa PLA normal). Las piezas de la pinza original no se imprimen.
A4: Gramos estimados | B4: =SUM(G13:G41)
A5: Gramos con merma | B5: =B4*(1+MermaImpresion)
A6: Rollos de 1 kg a comprar | B6: =ROUNDUP(B5/GramosRollo,0) | C6: ← lo lee VAR-01 (filamento) en la lista de materiales
A7: Horas de impresión | B7: =SUM(I13:I41)
A8: Avance (gramos impresos) | B8: =IF(B4>0,SUMIFS(G13:G41,J13:J41,"Impreso")/B4,0)
A9: Costo del filamento (USD) | B9: =IF('Lista de materiales'!$U$50="Ya lo tenemos",0,'Lista de materiales'!$T$50)
A12: # | B12: Pieza (STL) | C12: Subconjunto | D12: Cant. | E12: Volumen sólido (cm³) | F12: Gramos c/u | G12: Gramos total | H12: Horas c/u | I12: Horas total | J12: Estado | K12: Quién imprime | L12: Costo filamento (USD) | M12: Notas
A13: 1 | B13: Base | C13: Base | D13: 1 | E13: 501.5 | F13: 286.6 | G13: =D13*F13 | H13: =F13/RendimientoGH | I13: =D13*H13 | J13: Por imprimir | L13: =IF($B$6>0,G13*$B$9/($B$6*GramosRollo),0) | M13: Pieza más grande (≈32 h en el artículo)
A14: 2 | B14: Base cover | C14: Columna Z | D14: 1 | E14: 41.4 | F14: 50.9 | G14: =D14*F14 | H14: =F14/RendimientoGH | I14: =D14*H14 | J14: Por imprimir | L14: =IF($B$6>0,G14*$B$9/($B$6*GramosRollo),0)
A15: 3 | B15: J1 coupler | C15: Columna Z | D15: 1 | E15: 113.9 | F15: 73.3 | G15: =D15*F15 | H15: =F15/RendimientoGH | I15: =D15*H15 | J15: Por imprimir | L15: =IF($B$6>0,G15*$B$9/($B$6*GramosRollo),0)
A16: 4 | B16: Z-axis Bottom Plate | C16: Columna Z | D16: 1 | E16: 95.5 | F16: 57.9 | G16: =D16*F16 | H16: =F16/RendimientoGH | I16: =D16*H16 | J16: Por imprimir | L16: =IF($B$6>0,G16*$B$9/($B$6*GramosRollo),0)
A17: 5 | B17: Z-axis Top Plate | C17: Columna Z | D17: 1 | E17: 86.5 | F17: 55.1 | G17: =D17*F17 | H17: =F17/RendimientoGH | I17: =D17*H17 | J17: Por imprimir | L17: =IF($B$6>0,G17*$B$9/($B$6*GramosRollo),0)
A18: 6 | B18: Top cover | C18: Columna Z | D18: 1 | E18: 45.1 | F18: 54.3 | G18: =D18*F18 | H18: =F18/RendimientoGH | I18: =D18*H18 | J18: Por imprimir | L18: =IF($B$6>0,G18*$B$9/($B$6*GramosRollo),0)
A19: 7 | B19: Smooth Rod Clamp | C19: Columna Z | D19: 8 | E19: 8.2 | F19: 6.7 | G19: =D19*F19 | H19: =F19/RendimientoGH | I19: =D19*H19 | J19: Por imprimir | L19: =IF($B$6>0,G19*$B$9/($B$6*GramosRollo),0)
A20: 8 | B20: Z-axis Mount Platform | C20: Brazo 1 | D20: 1 | E20: 173.1 | F20: 129.3 | G20: =D20*F20 | H20: =F20/RendimientoGH | I20: =D20*H20 | J20: Por imprimir | L20: =IF($B$6>0,G20*$B$9/($B$6*GramosRollo),0)
A21: 9 | B21: Arm 1 | C21: Brazo 1 | D21: 1 | E21: 203.4 | F21: 135.6 | G21: =D21*F21 | H21: =F21/RendimientoGH | I21: =D21*H21 | J21: Por imprimir | L21: =IF($B$6>0,G21*$B$9/($B$6*GramosRollo),0)
A22: 10 | B22: Arm 1 Cover | C22: Brazo 1 | D22: 1 | E22: 48.2 | F22: 49.6 | G22: =D22*F22 | H22: =F22/RendimientoGH | I22: =D22*H22 | J22: Por imprimir | L22: =IF($B$6>0,G22*$B$9/($B$6*GramosRollo),0)
A23: 11 | B23: J2 Coupler | C23: Brazo 2 | D23: 1 | E23: 56 | F23: 38.9 | G23: =D23*F23 | H23: =F23/RendimientoGH | I23: =D23*H23 | J23: Por imprimir | L23: =IF($B$6>0,G23*$B$9/($B$6*GramosRollo),0)
A24: 12 | B24: Arm 2 | C24: Brazo 2 | D24: 1 | E24: 154.2 | F24: 117.9 | G24: =D24*F24 | H24: =F24/RendimientoGH | I24: =D24*H24 | J24: Por imprimir | L24: =IF($B$6>0,G24*$B$9/($B$6*GramosRollo),0)
A25: 13 | B25: Arm 2 Cover | C25: Brazo 2 | D25: 1 | E25: 109.3 | F25: 71.3 | G25: =D25*F25 | H25: =F25/RendimientoGH | I25: =D25*H25 | J25: Por imprimir | L25: =IF($B$6>0,G25*$B$9/($B$6*GramosRollo),0)
... A32: 20 | B32: GT2 Pulley - 90 teeth - J3 | C32: Transmisión | D32: 1 | E32: 24.6 | F32: 19.5 | G32: =D32*F32 | H32: =F32/RendimientoGH | I32: =D32*H32 | J32: Por imprimir | L32: =IF($B$6>0,G32*$B$9/($B$6*GramosRollo),0)
A33: 21 | B33: GT2 Pulley - Parametric | C33: Transmisión | D33: 3 | E33: 1.8 | F33: 2 | G33: =D33*F33 | H33: =F33/RendimientoGH | I33: =D33*H33 | J33: Por imprimir | L33: =IF($B$6>0,G33*$B$9/($B$6*GramosRollo),0) | M33: Paramétrica de 20 dientes: una por motor (J1, J2, J3)
A34: 22 | B34: Arduino UNO case p1 | C34: Electrónica | D34: 1 | E34: 64.7 | F34: 52.1 | G34: =D34*F34 | H34: =F34/RendimientoGH | I34: =D34*H34 | J34: Por imprimir | L34: =IF($B$6>0,G34*$B$9/($B$6*GramosRollo),0)
A35: 23 | B35: Arduino UNO case p2 | C35: Electrónica | D35: 1 | E35: 33.7 | F35: 32.8 | G35: =D35*F35 | H35: =F35/RendimientoGH | I35: =D35*H35 | J35: Por imprimir | L35: =IF($B$6>0,G35*$B$9/($B$6*GramosRollo),0)
A36: 24 | B36: Wires holder | C36: Brazo 2 | D36: 1 | E36: 3.9 | F36: 3.9 | G36: =D36*F36 | H36: =F36/RendimientoGH | I36: =D36*H36 | J36: Por imprimir | L36: =IF($B$6>0,G36*$B$9/($B$6*GramosRollo),0)
A37: 25 | B37: Placa trébol del cabezal A v3 (6 mm, PETG) | C37: Cabezal de disco | D37: 1 | E37: 35.8 | F37: 31.5 | G37: =D37*F37 | H37: =F37/RendimientoGH | I37: =D37*H37 | J37: Por imprimir | L37: =IF($B$6>0,G37*$B$9/($B$6*GramosRollo),0) | M37: STL en BRAZO SCARA/DISEÑO FINAL/Cabezal disco/STL/02_placa_trebol.stl · boca abajo, sin soportes
A38: 26 | B38: Separador de brida 14 mm (PETG) | C38: Cabezal de disco | D38: 1 | E38: 9.7 | F38: 12.4 | G38: =D38*F38 | H38: =F38/RendimientoGH | I38: =D38*H38 | J38: Por imprimir | L38: =IF($B$6>0,G38*$B$9/($B$6*GramosRollo),0) | M38: STL en BRAZO SCARA/DISEÑO FINAL/Cabezal disco/STL/01_separador_brida.stl · baja la placa 14 mm para no chocar con la cubierta del brazo 2
A39: 27 | B39: Soporte plumón/servo + puente + collar (PETG, 3 piezas) | C39: Cabezal de disco | D39: 1 | E39: 9.7 | F39: 11.8 | G39: =D39*F39 | H39: =F39/RendimientoGH | I39: =D39*H39 | J39: Por imprimir | L39: =IF($B$6>0,G39*$B$9/($B$6*GramosRollo),0) | M39: STL en BRAZO SCARA/DISEÑO FINAL/Cabezal disco/STL/03, 04 y 05 · gramos de las tres piezas
A40: 28 | B40: Separador del electroimán con copa (PLA+) | C40: Cabezal de disco | D40: 1 | E40: 6.5 | F40: 6 | G40: =D40*F40 | H40: =F40/RendimientoGH | I40: =D40*H40 | J40: Por imprimir | L40: =IF($B$6>0,G40*$B$9/($B$6*GramosRollo),0) | M40: STL en BRAZO SCARA/DISEÑO FINAL/Cabezal disco/STL/06_separador_electroiman.stl · reemplaza el separador M4 × 25
A41: 29 | B41: Abrazadera M12 del sensor (PLA+) | C41: Cabezal de disco | D41: 1 | E41: 6.9 | F41: 6.1 | G41: =D41*F41 | H41: =F41/RendimientoGH | I41: =D41*H41 | J41: Por imprimir | L41: =IF($B$6>0,G41*$B$9/($B$6*GramosRollo),0) | M41: STL en BRAZO SCARA/DISEÑO FINAL/Cabezal disco/STL/07_abrazadera_sensor_M12.stl
B42: Total | D42: =SUM(D13:D41) | G42: =SUM(G13:G41) | I42: =SUM(I13:I41) | L42: =SUM(L13:L41)

Sheet Supuestos
A1: Supuestos y parámetros
A2: Celdas amarillas con texto azul = editables. Todas las fórmulas del libro las usan por nombre.
A4: Nombre | B4: Parámetro | C4: Valor | D4: Fuente / nota
A5: TasaVentasEEUU | B5: Impuesto de venta en EE. UU. (Florida, casillero en Miami) | C5: 0.07 | D5: Amazon cobra el impuesto del estado de la dirección de entrega. Florida 6 % + condado Miami-Dade 1 %.
A6: FleteLb | B6: Flete del casillero (USD por libra) | C6: 2.5 | D6: QuickBox: USD 2.50 + IVA por libra o fracción, sin impuestos ni gestión (tiktok.com/@quickboxusa, 2026).
A7: IVA | B7: IVA El Salvador | C7: 0.13 | D7: Se cobra sobre el flete del casillero y en aduana.
A8: RecargoCIF | B8: Recargo aduanal sobre el valor (flete 10 % + seguro 1.5 %) | C8: 0.115 | D8: Compras personales < USD 300: IVA 13 % sobre valor + 10 % + 1.5 % (elsalvador.com, 2026).
A9: LimiteFranquicia | B9: Límite por envío para pagar solo IVA (USD) | C9: 300 | D9: Por encima aplica DAI: dividir en dos envíos.
A10: EnviosCasillero | B10: Número de envíos consolidados desde Amazon | C10: 1 | D10: Todo lo de Amazon (≈USD 190) cabe en un envío bajo el límite de USD 300.
A11: GestionEnvio | B11: Gestión del casillero por envío (USD) | C11: 3.5 | D11: Estimado: varía por empresa; preguntar al abrir el casillero.
A12: DescCasaRivas | B12: Descuento estudiantil Casa Rivas | C12: 0.25 | D12: Con carné. Se aplica solo a filas cuya tienda dice 'Casa Rivas'.
A13: Contingencia | B13: Contingencia sobre lo pendiente | C13: 0.1 | D13: Piezas que se rompen, reimpresiones, envíos extra.
A14: Integrantes | B14: Integrantes del equipo | C14: 4 | D14: Para dividir el costo.
A15: Presupuesto | B15: Presupuesto total del equipo (USD) | C15: 300 | D15: Editar con el monto acordado.
A16: MermaImpresion | B16: Merma de impresión (pruebas, soportes, fallos) | C16: 0.12 | D16: Sobre los gramos estimados.
A17: RendimientoGH | B17: Rendimiento de impresión (g por hora) | C17: 11.7 | D17: Calibrado con las 120 h que reporta HowToMechatronics para las piezas del robot.
A18: GramosRollo | B18: Gramos por rollo de filamento | C18: 1000
A21: Integrantes del equipo
A22: Escriban sus nombres: se usan en 'Registro de gastos' y en el resumen por persona.
B23: Integrante 1
B24: Integrante 2
B25: Integrante 3
B26: Integrante 4
A28: Fórmula del costo Amazon puesto en El Salvador (por paquete)
A29: precio × (1 + impuesto EE. UU.) + peso lb × flete × (1 + IVA) + precio × (1 + recargo CIF) × IVA. No incluye DAI: mantengan cada envío bajo el límite de la franquicia.
A30: Herramientas que se asumen disponibles (no presupuestadas): cautín, multímetro, llaves Allen, sierra para metal, impresora 3D. Precios consultados el 06-oct-2026.

Sheet Tiendas
A1: Dónde comprar
A2: Tiendas de El Salvador y la ruta de importación. Precios verificados en línea solo donde la hoja lo indica.
A4: Tienda | B4: Tipo | C4: Qué comprar ahí | D4: Dirección | E4: Teléfono | F4: Web / redes | G4: Notas
A5: Electrónica 2001 | B5: Electrónica / robótica | C5: NEMA 17 (USD 12, cód. 04-355), Arduino Mega, kits | D5: Calle Arce y 11 Av. Sur #635, San Salvador | E5: 2133-2001 | F5: electronica2001es.com | G5: Catálogo en línea con precios.
A6: Steren El Salvador | B6: Electrónica | C6: Placa ARD-010, fuente 12 V 5 A, micro switches, Dupont, cinchos | D6: Paseo Gral. Escalón y 87 Av. Norte, Col. Escalón | E6: 7876-4626 (WhatsApp) | F6: steren.com.sv | G6: Precios en línea; parte de la línea de motores aparece agotada.
A7: Casa Rivas Electrónica | B7: Componentes sueltos | C7: MOSFET, diodos, PC817, buck, placa perforada, jack DC, servos hobby | D7: 2ª Av. Norte #312 (frente a Lotería Nacional) + 3 sucursales | E7: 2222-1718 · WhatsApp 6836-5980 | F7: — | G7: 25 % de descuento a estudiantes con carné (aplicado en la hoja).
A8: ArduStore SV | B8: Módulos Arduino | C8: CNC Shield, drivers A4988, LM2596 | D8: En línea (redes sociales) | E8: 6967-8072 | F8: facebook.com/ardustore.sv | G8: Pedidos por mensaje directo.
A9: Creativo 3D | B9: Impresión 3D y repuestos | C9: Varillas 10 mm, LM10UU, husillo T8, acople, correas GT2, NEMA | D9: San Salvador | E9: Pedidos 7718-6482 · Consultas 7235-4757 | F9: IG @creativo3d_sv | G9: Reparan impresoras: la llamada que decide si se compra local.
A10: CEROSA | B10: Rodamientos | C10: 51108, 51107, 6807, 6806, 608ZZ, LM10UU | D10: Blvd. Venezuela #3077, San Salvador | E10: — | F10: cerosa.com | G10: Llevar las medidas; cotizar también en RODASA y REPSA.
A11: Almacenes Vidrí | B11: Ferretería | C11: Tornillería M3–M8, madera/MDF, resortes, cable multiconductor | D11: Varias sucursales | E11: — | F11: vidri.com.sv | G11: Catálogo en línea; retiro en 2 h.
A12: Prestelectro / Intek | B12: Sensores industriales | C12: Sensor inductivo (USD 25–60) | D12: San Salvador | E12: 2222-1212 / 2260-8888 | F12: prestelectro.com | G12: Solo si no quieren importar el LJ12A3.
A13: El Changarro | B13: Tienda en línea | C13: Filamento PLA 1 kg (USD 27.99 en oferta) | D13: En línea | E13: — | F13: elchangarro.com.sv | G13: Precio indexado; confirmar.
A14: Amazon + casillero | B14: Importación | C14: Lo que no hay en el país: electroimán, sensor, CNC Shield, rodamientos, varillas, correas | D14: Casillero en Miami (p. ej. QuickBox) | E14: — | F14: amazon.com | G14: ≈ USD 2.50 + IVA por libra; compras < USD 300 solo pagan 13 % de IVA.
